{"id": "65--14", "latMin": 65, "lonMin": -14, "latMax": 66, "lonMax": -13, "generated": "2026-04-16T18:39:08.808Z", "count": 7, "pois": [{"type": "node", "id": 6721193272, "lat": 65.260366, "lon": -14.408244, "tags": {"amenity": "charging_station", "operator": "Orka náttúrunnar", "name": "ON", "capacity": "3", "_source": "worldwide"}}, {"type": "node", "id": 9891073360, "lat": 65.259394, "lon": -14.406497, "tags": {"amenity": "charging_station", "access": "customers", "fee": "yes", "brand": "Tesla Supercharger", "opening_hours": "24/7", "operator": "Tesla", "name": "Egilsstaðir Supercharger", "addr:street": "Kaupvangur 9", "addr:postcode": "700", "addr:city": "Egilsstaðir", "addr:country": "IS", "socket:type2_combo": "2", "socket:type2_combo:output": "150.0 kW", "socket:tesla_supercharger": "2", "socket:tesla_supercharger:output": "150.0 kW", "charging_station:output": "150.0 kW", "capacity": "2", "_source": "worldwide"}}, {"type": "node", "id": 11055291745, "lat": 65.303331, "lon": -14.445445, "tags": {"amenity": "charging_station", "access": "permissive", "fee": "yes", "brand": "ON", "operator": "Orka náttúrunnar", "name": "Vök Baths - Hverfahleðsla", "socket:type2": "10", "socket:type2:output": "22.0 kW", "charging_station:output": "22.0 kW", "capacity": "10", "_source": "worldwide"}}, {"type": "node", "id": 12641726922, "lat": 65.033816, "lon": -14.231242, "tags": {"amenity": "charging_station", "fee": "yes", "socket:type2_combo": "1", "socket:type2_combo:output": "50 kW", "socket:chademo": "1", "socket:chademo:output": "50 kW", "charging_station:output": "50 kW", "capacity": "2", "_source": "worldwide"}}, {"type": "node", "id": 12643895840, "lat": 65.257818, "lon": -14.412917, "tags": {"amenity": "charging_station", "operator": "Orka", "name": "Ladestation Orka", "socket:type2_combo": "2", "socket:type2_combo:output": "150.0 kW", "socket:chademo": "1", "socket:chademo:output": "50 kW", "charging_station:output": "150.0 kW", "capacity": "2", "_source": "worldwide"}}, {"type": "node", "id": 12646470071, "lat": 65.260063, "lon": -14.009113, "tags": {"amenity": "charging_station", "fee": "yes", "operator": "ísorka", "name": "Ladestation ísorka", "socket:type2_combo": "1", "socket:type2_combo:output": "50 kW", "socket:chademo": "1", "socket:chademo:output": "50 kW", "charging_station:output": "50 kW", "capacity": "2", "_source": "worldwide"}}, {"type": "node", "id": 12646533252, "lat": 65.267151, "lon": -14.395888, "tags": {"amenity": "charging_station", "fee": "yes", "socket:type2": "2", "socket:type2:output": "22.0 kW", "charging_station:output": "22.0 kW", "capacity": "2", "_source": "worldwide"}}]}