{"id": "35-139", "latMin": 35, "lonMin": 139, "latMax": 36, "lonMax": 140, "generated": "2026-04-16T18:39:07.373Z", "count": 175, "pois": [{"type": "node", "id": 1936276034, "lat": 35.711786, "lon": 139.979327, "tags": {"amenity": "charging_station", "name": "EV Charging Station", "_source": "worldwide"}}, {"type": "node", "id": 2975719253, "lat": 35.711291, "lon": 139.9825, "tags": {"amenity": "charging_station", "name": "EV Charging Station", "_source": "worldwide"}}, {"type": "node", "id": 3069999478, "lat": 35.659376, "lon": 139.72843, "tags": {"amenity": "charging_station", "fee": "yes", "access": "customers", "opening_hours": "24/7", "brand": "Tesla Supercharger", "operator": "Tesla", "name": "Tesla Supercharger Hyatt Tokyo", "capacity": "2", "_source": "worldwide"}}, {"type": "node", "id": 3070008221, "lat": 35.425633, "lon": 139.537506, "tags": {"amenity": "charging_station", "fee": "yes", "access": "yes", "opening_hours": "24/7", "name": "EV Charging Station", "_source": "worldwide"}}, {"type": "node", "id": 3610344759, "lat": 35.48878, "lon": 139.464097, "tags": {"amenity": "charging_station", "name": "EV Charging Station", "_source": "worldwide"}}, {"type": "node", "id": 3669017119, "lat": 35.487059, "lon": 139.457889, "tags": {"amenity": "charging_station", "name": "EV Charging Station", "_source": "worldwide"}}, {"type": "node", "id": 3751941188, "lat": 35.677036, "lon": 139.370734, "tags": {"amenity": "charging_station", "name": "EV Charging Station", "_source": "worldwide"}}, {"type": "node", "id": 3751941194, "lat": 35.679843, "lon": 139.3739, "tags": {"amenity": "charging_station", "name": "EV Charging Station", "_source": "worldwide"}}, {"type": "node", "id": 3760204635, "lat": 35.626814, "lon": 139.045015, "tags": {"amenity": "charging_station", "name": "EV Charging Station", "_source": "worldwide"}}, {"type": "node", "id": 3761192170, "lat": 35.633062, "lon": 139.063795, "tags": {"amenity": "charging_station", "name": "EV Charging Station", "_source": "worldwide"}}, {"type": "node", "id": 3783030235, "lat": 35.382757, "lon": 139.49841, "tags": {"amenity": "charging_station", "name": "EV Charging Station", "_source": "worldwide"}}, {"type": "node", "id": 3864821586, "lat": 35.543402, "lon": 139.6029, "tags": {"amenity": "charging_station", "name": "EV Charging Station", "_source": "worldwide"}}, {"type": "node", "id": 3864821604, "lat": 35.482286, "lon": 139.595456, "tags": {"amenity": "charging_station", "name": "EV Charging Station", "_source": "worldwide"}}, {"type": "node", "id": 3907557343, "lat": 35.142783, "lon": 139.844365, "tags": {"amenity": "charging_station", "name": "EV Charging Station", "_source": "worldwide"}}, {"type": "node", "id": 3925017136, "lat": 35.592661, "lon": 139.738346, "tags": {"amenity": "charging_station", "name": "EV Charging Station", "_source": "worldwide"}}, {"type": "node", "id": 3928753097, "lat": 35.419552, "lon": 139.468717, "tags": {"amenity": "charging_station", "name": "EV Charging Station", "_source": "worldwide"}}, {"type": "node", "id": 3994537957, "lat": 35.519116, "lon": 139.472014, "tags": {"amenity": "charging_station", "name": "EV Charging Station", "_source": "worldwide"}}, {"type": "node", "id": 4057899406, "lat": 35.535165, "lon": 139.533286, "tags": {"amenity": "charging_station", "name": "EV Charging Station", "_source": "worldwide"}}, {"type": "node", "id": 4068196070, "lat": 35.186803, "lon": 139.015332, "tags": {"amenity": "charging_station", "name": "EV Charging Station", "_source": "worldwide"}}, {"type": "node", "id": 4068349281, "lat": 35.318199, "lon": 139.26898, "tags": {"amenity": "charging_station", "name": "EV Charging Station", "_source": "worldwide"}}, {"type": "node", "id": 4079727314, "lat": 35.461726, "lon": 139.679558, "tags": {"amenity": "charging_station", "name": "EV Charging Station", "_source": "worldwide"}}, {"type": "node", "id": 4155295365, "lat": 35.250261, "lon": 139.644353, "tags": {"amenity": "charging_station", "name": "EV Charging Station", "_source": "worldwide"}}, {"type": "node", "id": 4155295379, "lat": 35.253117, "lon": 139.638942, "tags": {"amenity": "charging_station", "name": "EV Charging Station", "_source": "worldwide"}}, {"type": "node", "id": 4172672683, "lat": 35.851572, "lon": 139.365134, "tags": {"amenity": "charging_station", "name": "EV Charging Station", "_source": "worldwide"}}, {"type": "node", "id": 4172672686, "lat": 35.852143, "lon": 139.367377, "tags": {"amenity": "charging_station", "name": "EV Charging Station", "_source": "worldwide"}}, {"type": "node", "id": 4195217510, "lat": 35.871375, "lon": 139.503227, "tags": {"amenity": "charging_station", "name": "EV Charging Station", "_source": "worldwide"}}, {"type": "node", "id": 4249994376, "lat": 35.525597, "lon": 139.466203, "tags": {"amenity": "charging_station", "name": "EV Charging Station", "_source": "worldwide"}}, {"type": "node", "id": 4348248472, "lat": 35.482322, "lon": 139.276738, "tags": {"amenity": "charging_station", "opening_hours": "08:30-17:00", "name": "EV Charging Station", "_source": "worldwide"}}, {"type": "node", "id": 4348351843, "lat": 35.491303, "lon": 139.369479, "tags": {"amenity": "charging_station", "name": "EV Charging Station", "_source": "worldwide"}}, {"type": "node", "id": 4358607000, "lat": 35.363068, "lon": 139.306831, "tags": {"amenity": "charging_station", "name": "EV Charging Station", "_source": "worldwide"}}, {"type": "node", "id": 4358899645, "lat": 35.380177, "lon": 139.031528, "tags": {"amenity": "charging_station", "name": "EV Charging Station", "_source": "worldwide"}}, {"type": "node", "id": 4369601219, "lat": 35.342354, "lon": 139.203024, "tags": {"amenity": "charging_station", "name": "EV Charging Station", "_source": "worldwide"}}, {"type": "node", "id": 4376688195, "lat": 35.74609, "lon": 139.765795, "tags": {"amenity": "charging_station", "name": "東京電力", "_source": "worldwide"}}, {"type": "node", "id": 4376702989, "lat": 35.746057, "lon": 139.76638, "tags": {"amenity": "charging_station", "name": "KDDI新東京北別館ネットワークセンター", "_source": "worldwide"}}, {"type": "node", "id": 4382964688, "lat": 35.489889, "lon": 139.368928, "tags": {"amenity": "charging_station", "name": "EV Charging Station", "_source": "worldwide"}}, {"type": "node", "id": 4500355921, "lat": 35.433159, "lon": 139.400267, "tags": {"amenity": "charging_station", "name": "EV Charging Station", "_source": "worldwide"}}, {"type": "node", "id": 4620676733, "lat": 35.440215, "lon": 139.434813, "tags": {"amenity": "charging_station", "name": "EV Charging Station", "_source": "worldwide"}}, {"type": "node", "id": 4727917345, "lat": 35.859691, "lon": 139.829396, "tags": {"amenity": "charging_station", "name": "EV Charging Station", "_source": "worldwide"}}, {"type": "node", "id": 4784010373, "lat": 35.817791, "lon": 139.676745, "tags": {"amenity": "charging_station", "name": "EV Charging Station", "_source": "worldwide"}}, {"type": "node", "id": 4839852051, "lat": 35.843805, "lon": 139.853144, "tags": {"amenity": "charging_station", "name": "EV Charging Station", "_source": "worldwide"}}, {"type": "node", "id": 4839852054, "lat": 35.843742, "lon": 139.853164, "tags": {"amenity": "charging_station", "name": "EV Charging Station", "_source": "worldwide"}}, {"type": "node", "id": 4839852066, "lat": 35.843489, "lon": 139.853252, "tags": {"amenity": "charging_station", "name": "EV Charging Station", "_source": "worldwide"}}, {"type": "node", "id": 4894889532, "lat": 35.695725, "lon": 139.982714, "tags": {"amenity": "charging_station", "fee": "no", "name": "EV Charging Station", "_source": "worldwide"}}, {"type": "node", "id": 4971588376, "lat": 35.586078, "lon": 139.742662, "tags": {"amenity": "charging_station", "name": "EV Charging Station", "_source": "worldwide"}}, {"type": "node", "id": 4971914571, "lat": 35.940902, "lon": 139.967929, "tags": {"amenity": "charging_station", "name": "EV Charging Station", "_source": "worldwide"}}, {"type": "node", "id": 4973487710, "lat": 35.940189, "lon": 139.969694, "tags": {"amenity": "charging_station", "name": "EV Charging Station", "_source": "worldwide"}}, {"type": "node", "id": 4973577451, "lat": 35.809402, "lon": 139.842605, "tags": {"amenity": "charging_station", "name": "EV Charging Station", "_source": "worldwide"}}, {"type": "node", "id": 5040405961, "lat": 35.626612, "lon": 139.631265, "tags": {"amenity": "charging_station", "name": "EV Charging Station", "_source": "worldwide"}}, {"type": "node", "id": 5466272043, "lat": 35.547783, "lon": 139.556721, "tags": {"amenity": "charging_station", "access": "customers", "network": "ジャパンチャージネットワーク", "operator": "ファミリーマート", "name": "ファミリーマート", "_source": "worldwide"}}, {"type": "node", "id": 5592314269, "lat": 35.67774, "lon": 139.933232, "tags": {"amenity": "charging_station", "name": "EV Charging Station", "_source": "worldwide"}}, {"type": "node", "id": 5821695499, "lat": 35.956775, "lon": 139.40269, "tags": {"amenity": "charging_station", "operator": "EV充電器", "name": "EV充電器", "_source": "worldwide"}}, {"type": "node", "id": 5909130574, "lat": 35.847664, "lon": 139.92588, "tags": {"amenity": "charging_station", "name": "EV Charging Station", "_source": "worldwide"}}, {"type": "node", "id": 6036379326, "lat": 35.483111, "lon": 139.276414, "tags": {"amenity": "charging_station", "name": "EV Charging Station", "_source": "worldwide"}}, {"type": "node", "id": 6048149320, "lat": 35.607292, "lon": 139.683202, "tags": {"amenity": "charging_station", "operator": "大和ハウスパーキング", "name": "大和ハウスパーキング", "_source": "worldwide"}}, {"type": "node", "id": 6052369943, "lat": 35.471371, "lon": 139.314624, "tags": {"amenity": "charging_station", "name": "EV Charging Station", "_source": "worldwide"}}, {"type": "node", "id": 6070309088, "lat": 35.460828, "lon": 139.358145, "tags": {"amenity": "charging_station", "name": "EV Charging Station", "_source": "worldwide"}}, {"type": "node", "id": 6072165986, "lat": 35.591777, "lon": 139.675709, "tags": {"amenity": "charging_station", "operator": "ローソン田園調布一丁目店", "name": "ローソン田園調布一丁目店", "_source": "worldwide"}}, {"type": "node", "id": 6170147682, "lat": 35.681265, "lon": 139.698044, "tags": {"amenity": "charging_station", "name": "EV Charging Station", "_source": "worldwide"}}, {"type": "node", "id": 6170336081, "lat": 35.77396, "lon": 139.685183, "tags": {"amenity": "charging_station", "name": "EV Charging Station", "_source": "worldwide"}}, {"type": "node", "id": 6433502302, "lat": 35.88074, "lon": 139.827467, "tags": {"amenity": "charging_station", "name": "EV Charging Station", "_source": "worldwide"}}, {"type": "node", "id": 6438702033, "lat": 35.26731, "lon": 139.00614, "tags": {"amenity": "charging_station", "name": "EV Charging Station", "_source": "worldwide"}}, {"type": "node", "id": 6598838068, "lat": 35.778543, "lon": 139.757339, "tags": {"amenity": "charging_station", "name": "EV Charging Station", "_source": "worldwide"}}, {"type": "node", "id": 6603167674, "lat": 35.532191, "lon": 139.267476, "tags": {"amenity": "charging_station", "fee": "no", "opening_hours": "Tu-Su 09:00-17:00", "name": "EV Charging Station", "_source": "worldwide"}}, {"type": "node", "id": 6612547167, "lat": 35.769541, "lon": 139.803718, "tags": {"amenity": "charging_station", "name": "EV Charging Station", "_source": "worldwide"}}, {"type": "node", "id": 6792460746, "lat": 35.681842, "lon": 139.552022, "tags": {"amenity": "charging_station", "name": "EV Charging Station", "_source": "worldwide"}}, {"type": "node", "id": 6792460751, "lat": 35.681345, "lon": 139.557242, "tags": {"amenity": "charging_station", "name": "EV Charging Station", "_source": "worldwide"}}, {"type": "node", "id": 6794439452, "lat": 35.687191, "lon": 139.56856, "tags": {"amenity": "charging_station", "name": "EV Charging Station", "_source": "worldwide"}}, {"type": "node", "id": 6844710647, "lat": 35.975698, "lon": 139.752128, "tags": {"amenity": "charging_station", "name": "EV充電", "_source": "worldwide"}}, {"type": "node", "id": 6934695493, "lat": 35.749248, "lon": 139.92005, "tags": {"amenity": "charging_station", "name": "EV Charging Station", "_source": "worldwide"}}, {"type": "node", "id": 6970356855, "lat": 35.734585, "lon": 139.529032, "tags": {"amenity": "charging_station", "name": "EV Charging Station", "_source": "worldwide"}}, {"type": "node", "id": 7007243309, "lat": 35.667101, "lon": 139.728281, "tags": {"amenity": "charging_station", "name": "EV充電スポット", "_source": "worldwide"}}, {"type": "node", "id": 7015935296, "lat": 35.667028, "lon": 139.727869, "tags": {"amenity": "charging_station", "name": "EV Charging Station", "_source": "worldwide"}}, {"type": "node", "id": 7074394654, "lat": 35.595658, "lon": 139.372658, "tags": {"amenity": "charging_station", "name": "EV Charging Station", "_source": "worldwide"}}, {"type": "node", "id": 7314016705, "lat": 35.551035, "lon": 139.784627, "tags": {"amenity": "charging_station", "fee": "no", "access": "customers", "brand": "東光高岳", "operator": "東光高岳", "name": "東光高岳", "_source": "worldwide"}}, {"type": "node", "id": 7314016706, "lat": 35.548343, "lon": 139.786568, "tags": {"amenity": "charging_station", "fee": "no", "access": "customers", "brand": "東光高岳", "operator": "東光高岳", "name": "東光高岳", "_source": "worldwide"}}, {"type": "node", "id": 7314016713, "lat": 35.549719, "lon": 139.788204, "tags": {"amenity": "charging_station", "fee": "no", "access": "customers", "brand": "東光高岳", "operator": "東光高岳", "name": "東光高岳", "_source": "worldwide"}}, {"type": "node", "id": 7314016719, "lat": 35.551819, "lon": 139.786135, "tags": {"amenity": "charging_station", "fee": "no", "access": "customers", "brand": "東光高岳", "operator": "東光高岳", "name": "東光高岳", "_source": "worldwide"}}, {"type": "node", "id": 7314017257, "lat": 35.543399, "lon": 139.768015, "tags": {"amenity": "charging_station", "fee": "no", "access": "customers", "brand": "東光高岳", "operator": "東光高岳", "name": "東光高岳", "_source": "worldwide"}}, {"type": "node", "id": 7314134091, "lat": 35.495628, "lon": 139.763076, "tags": {"amenity": "charging_station", "name": "東光高岳", "_source": "worldwide"}}, {"type": "node", "id": 7316652863, "lat": 35.480101, "lon": 139.688299, "tags": {"amenity": "charging_station", "name": "東光高岳", "_source": "worldwide"}}, {"type": "node", "id": 7436152343, "lat": 35.991999, "lon": 139.610217, "tags": {"amenity": "charging_station", "name": "トヨタEV充電スポット", "_source": "worldwide"}}, {"type": "node", "id": 7441571277, "lat": 35.999478, "lon": 139.624189, "tags": {"amenity": "charging_station", "name": "EV充電スポット", "_source": "worldwide"}}, {"type": "node", "id": 7779695643, "lat": 35.571567, "lon": 139.443086, "tags": {"amenity": "charging_station", "operator": "東京日産本町田店", "name": "EV QUICK", "_source": "worldwide"}}, {"type": "node", "id": 7918855186, "lat": 35.442861, "lon": 139.395284, "tags": {"amenity": "charging_station", "name": "EV Charging Station", "_source": "worldwide"}}, {"type": "node", "id": 8065974515, "lat": 35.439067, "lon": 139.466464, "tags": {"amenity": "charging_station", "access": "customers", "name": "EV Charging Station", "_source": "worldwide"}}, {"type": "node", "id": 8334123110, "lat": 35.996618, "lon": 139.794131, "tags": {"amenity": "charging_station", "name": "EV Charging Station", "_source": "worldwide"}}, {"type": "node", "id": 8508664318, "lat": 35.782752, "lon": 139.918814, "tags": {"amenity": "charging_station", "name": "EV Charging Station", "_source": "worldwide"}}, {"type": "node", "id": 8508664319, "lat": 35.78439, "lon": 139.921363, "tags": {"amenity": "charging_station", "name": "EV Charging Station", "_source": "worldwide"}}, {"type": "node", "id": 8642092064, "lat": 35.546284, "lon": 139.438114, "tags": {"amenity": "charging_station", "name": "EV Charging Station", "_source": "worldwide"}}, {"type": "node", "id": 8946111481, "lat": 35.325826, "lon": 139.118318, "tags": {"amenity": "charging_station", "name": "EV Charging Station", "_source": "worldwide"}}, {"type": "node", "id": 9048643437, "lat": 35.997933, "lon": 139.088864, "tags": {"amenity": "charging_station", "name": "EV Charging Station", "_source": "worldwide"}}, {"type": "node", "id": 9081666999, "lat": 35.954346, "lon": 139.012902, "tags": {"amenity": "charging_station", "name": "EV Charging Station", "_source": "worldwide"}}, {"type": "node", "id": 9081667004, "lat": 35.977591, "lon": 139.134883, "tags": {"amenity": "charging_station", "name": "EV Charging Station", "_source": "worldwide"}}, {"type": "node", "id": 9081667005, "lat": 35.889664, "lon": 139.33161, "tags": {"amenity": "charging_station", "name": "EV Charging Station", "_source": "worldwide"}}, {"type": "node", "id": 9081667006, "lat": 35.87048, "lon": 139.332574, "tags": {"amenity": "charging_station", "name": "EV Charging Station", "_source": "worldwide"}}, {"type": "node", "id": 9081667007, "lat": 35.871289, "lon": 139.333526, "tags": {"amenity": "charging_station", "name": "EV Charging Station", "_source": "worldwide"}}, {"type": "node", "id": 9081667008, "lat": 35.855487, "lon": 139.328542, "tags": {"amenity": "charging_station", "name": "EV Charging Station", "_source": "worldwide"}}, {"type": "node", "id": 9177951400, "lat": 35.576249, "lon": 139.408356, "tags": {"amenity": "charging_station", "fee": "yes", "opening_hours": "24/7", "name": "EV Charging Station", "socket:chademo": "1", "capacity": "1", "_source": "worldwide"}}, {"type": "node", "id": 9394157563, "lat": 35.784186, "lon": 139.255724, "tags": {"amenity": "charging_station", "access": "customers", "name": "EV 200V", "_source": "worldwide"}}, {"type": "node", "id": 9572102838, "lat": 35.533282, "lon": 139.716892, "tags": {"amenity": "charging_station", "operator": "Nissan", "name": "Nissan", "_source": "worldwide"}}, {"type": "node", "id": 9743634472, "lat": 35.626578, "lon": 139.714194, "tags": {"amenity": "charging_station", "name": "EV Charging Station", "socket:chademo": "1", "capacity": "1", "_source": "worldwide"}}, {"type": "node", "id": 9743660790, "lat": 35.649884, "lon": 139.699968, "tags": {"amenity": "charging_station", "fee": "yes", "name": "EV Charging Station", "socket:tesla_supercharger": "4", "capacity": "4", "_source": "worldwide"}}, {"type": "node", "id": 9749255591, "lat": 35.606333, "lon": 139.747059, "tags": {"amenity": "charging_station", "name": "EV Charging Station", "socket:chademo": "1", "capacity": "1", "_source": "worldwide"}}, {"type": "node", "id": 9790467795, "lat": 35.586778, "lon": 139.410965, "tags": {"amenity": "charging_station", "name": "EV Charging Station", "_source": "worldwide"}}, {"type": "node", "id": 9845797949, "lat": 35.489264, "lon": 139.456588, "tags": {"amenity": "charging_station", "name": "EV Charging Station", "_source": "worldwide"}}, {"type": "node", "id": 9964947132, "lat": 35.334328, "lon": 139.862584, "tags": {"amenity": "charging_station", "brand": "東光高岳", "operator": "東光高岳", "name": "東光高岳", "_source": "worldwide"}}, {"type": "node", "id": 10140192420, "lat": 35.544156, "lon": 139.568738, "tags": {"amenity": "charging_station", "name": "EV Charging Station", "_source": "worldwide"}}, {"type": "node", "id": 10273727836, "lat": 35.663074, "lon": 139.525048, "tags": {"amenity": "charging_station", "fee": "yes", "name": "EV Charging Station", "socket:tesla_supercharger": "4", "capacity": "4", "_source": "worldwide"}}, {"type": "node", "id": 10285546619, "lat": 35.579389, "lon": 139.784611, "tags": {"amenity": "charging_station", "name": "EV Charging Station", "_source": "worldwide"}}, {"type": "node", "id": 10674967188, "lat": 35.778601, "lon": 139.497264, "tags": {"amenity": "charging_station", "name": "EV Charging Station", "_source": "worldwide"}}, {"type": "node", "id": 11689960801, "lat": 35.929048, "lon": 139.466834, "tags": {"amenity": "charging_station", "fee": "yes", "brand": "ENEOS", "operator": "ENEOS Dr.Driveセルフ川越上寺山店", "name": "ENEOS", "_source": "worldwide"}}, {"type": "node", "id": 11834837719, "lat": 35.892112, "lon": 139.947246, "tags": {"amenity": "charging_station", "access": "private", "name": "EV Charging Station", "_source": "worldwide"}}, {"type": "node", "id": 11845467390, "lat": 35.688833, "lon": 139.81036, "tags": {"amenity": "charging_station", "name": "EV Charging Station", "_source": "worldwide"}}, {"type": "node", "id": 11910144403, "lat": 35.336914, "lon": 139.993502, "tags": {"amenity": "charging_station", "name": "EV Charging Station", "_source": "worldwide"}}, {"type": "node", "id": 11946675202, "lat": 35.556718, "lon": 139.430642, "tags": {"amenity": "charging_station", "name": "Ev Quick", "_source": "worldwide"}}, {"type": "node", "id": 12050668150, "lat": 35.332374, "lon": 139.916617, "tags": {"amenity": "charging_station", "name": "EV Charging Station", "_source": "worldwide"}}, {"type": "node", "id": 12107177336, "lat": 35.629231, "lon": 139.874088, "tags": {"amenity": "charging_station", "name": "EV Charging Station", "_source": "worldwide"}}, {"type": "node", "id": 12206433570, "lat": 35.895901, "lon": 139.953997, "tags": {"amenity": "charging_station", "name": "EV Charging Station", "_source": "worldwide"}}, {"type": "node", "id": 12206855227, "lat": 35.458161, "lon": 139.603056, "tags": {"amenity": "charging_station", "access": "yes", "brand": "トヨタEV充電スポット", "name": "トヨタEV充電スポット", "_source": "worldwide"}}, {"type": "node", "id": 12550840287, "lat": 35.322506, "lon": 139.924861, "tags": {"amenity": "charging_station", "brand": "ENEOS", "name": "ENEOS", "_source": "worldwide"}}, {"type": "node", "id": 12570337739, "lat": 35.682372, "lon": 139.734635, "tags": {"amenity": "charging_station", "fee": "yes", "access": "yes", "name": "EV Charging Station", "_source": "worldwide"}}, {"type": "node", "id": 12683656296, "lat": 35.774668, "lon": 139.504042, "tags": {"amenity": "charging_station", "access": "customers", "name": "EV Charging Station", "_source": "worldwide"}}, {"type": "node", "id": 12730199216, "lat": 35.793234, "lon": 139.316555, "tags": {"amenity": "charging_station", "brand": "e-Mobility Power", "operator": "株式会社イーモビリティパワー", "name": "e-Mobility Power", "_source": "worldwide"}}, {"type": "node", "id": 12747397444, "lat": 35.787774, "lon": 139.515909, "tags": {"amenity": "charging_station", "access": "yes", "name": "EV Charging Station", "_source": "worldwide"}}, {"type": "node", "id": 12785512569, "lat": 35.781905, "lon": 139.50007, "tags": {"amenity": "charging_station", "fee": "yes", "access": "customers", "name": "EV Charging Station", "_source": "worldwide"}}, {"type": "node", "id": 12860798817, "lat": 35.75687, "lon": 139.326549, "tags": {"amenity": "charging_station", "name": "EV Charging Station", "_source": "worldwide"}}, {"type": "node", "id": 12950669949, "lat": 35.545002, "lon": 139.764409, "tags": {"amenity": "charging_station", "fee": "yes", "access": "yes", "name": "EV Charging Station", "_source": "worldwide"}}, {"type": "node", "id": 12963820397, "lat": 35.401187, "lon": 139.469796, "tags": {"amenity": "charging_station", "name": "EV Charging Station", "_source": "worldwide"}}, {"type": "node", "id": 12987517704, "lat": 35.738338, "lon": 139.745983, "tags": {"amenity": "charging_station", "access": "private", "name": "EV Charging Station", "socket:chademo": "1", "capacity": "1", "_source": "worldwide"}}, {"type": "node", "id": 13078735930, "lat": 35.337841, "lon": 139.151999, "tags": {"amenity": "charging_station", "fee": "yes", "access": "yes", "opening_hours": "24/7", "brand": "Tesla Supercharger", "operator": "Tesla", "name": "Tesla Supercharger Oi - Matsuda, Japan", "addr:postcode": "2580019", "capacity": "6", "_source": "worldwide"}}, {"type": "node", "id": 13242826334, "lat": 35.757774, "lon": 139.326319, "tags": {"amenity": "charging_station", "name": "EV Charging Station", "_source": "worldwide"}}, {"type": "node", "id": 13354953486, "lat": 35.392794, "lon": 139.365857, "tags": {"amenity": "charging_station", "name": "EV Charging Station", "_source": "worldwide"}}, {"type": "node", "id": 13514161715, "lat": 35.320797, "lon": 139.378957, "tags": {"amenity": "charging_station", "name": "EV Charging Station", "_source": "worldwide"}}, {"type": "node", "id": 13689230202, "lat": 35.732379, "lon": 139.656539, "tags": {"amenity": "charging_station", "fee": "yes", "access": "yes", "opening_hours": "24/7", "name": "EV Charging Station", "_source": "worldwide"}}, {"type": "node", "id": 13689230203, "lat": 35.671275, "lon": 139.753281, "tags": {"amenity": "charging_station", "fee": "yes", "access": "yes", "opening_hours": "24/7", "name": "EV Charging Station", "_source": "worldwide"}}, {"type": "node", "id": 13689230204, "lat": 35.684842, "lon": 139.761048, "tags": {"amenity": "charging_station", "fee": "yes", "access": "yes", "opening_hours": "24/7", "name": "EV Charging Station", "_source": "worldwide"}}, {"type": "node", "id": 13689230901, "lat": 35.688214, "lon": 139.693101, "tags": {"amenity": "charging_station", "fee": "yes", "access": "yes", "opening_hours": "24/7", "name": "EV Charging Station", "_source": "worldwide"}}, {"type": "node", "id": 13689230902, "lat": 35.636522, "lon": 139.740086, "tags": {"amenity": "charging_station", "fee": "yes", "access": "yes", "opening_hours": "24/7", "brand": "Tesla Supercharger", "operator": "Tesla", "name": "Tesla Supercharger", "_source": "worldwide"}}, {"type": "node", "id": 13689231601, "lat": 35.728247, "lon": 139.707629, "tags": {"amenity": "charging_station", "fee": "yes", "access": "yes", "opening_hours": "24/7", "name": "EV Charging Station", "_source": "worldwide"}}, {"type": "node", "id": 13689231602, "lat": 35.679458, "lon": 139.768957, "tags": {"amenity": "charging_station", "fee": "yes", "access": "yes", "opening_hours": "24/7", "name": "EV Charging Station", "_source": "worldwide"}}, {"type": "node", "id": 13689231701, "lat": 35.667555, "lon": 139.741002, "tags": {"amenity": "charging_station", "fee": "yes", "access": "yes", "opening_hours": "24/7", "name": "EV Charging Station", "_source": "worldwide"}}, {"type": "node", "id": 13689231702, "lat": 35.622686, "lon": 139.658455, "tags": {"amenity": "charging_station", "fee": "yes", "access": "yes", "opening_hours": "24/7", "name": "EV Charging Station", "_source": "worldwide"}}, {"type": "node", "id": 13689241301, "lat": 35.714443, "lon": 139.616637, "tags": {"amenity": "charging_station", "fee": "yes", "access": "yes", "opening_hours": "24/7", "name": "EV Charging Station", "_source": "worldwide"}}, {"type": "node", "id": 13689241302, "lat": 35.770601, "lon": 139.691239, "tags": {"amenity": "charging_station", "fee": "yes", "access": "yes", "opening_hours": "24/7", "name": "EV Charging Station", "_source": "worldwide"}}, {"type": "node", "id": 13689243201, "lat": 35.700752, "lon": 139.772495, "tags": {"amenity": "charging_station", "fee": "yes", "access": "yes", "opening_hours": "24/7", "name": "EV Charging Station", "_source": "worldwide"}}, {"type": "node", "id": 13689243202, "lat": 35.667169, "lon": 139.613097, "tags": {"amenity": "charging_station", "fee": "yes", "access": "yes", "opening_hours": "24/7", "name": "EV Charging Station", "_source": "worldwide"}}, {"type": "node", "id": 13689245301, "lat": 35.636786, "lon": 139.619659, "tags": {"amenity": "charging_station", "fee": "yes", "access": "yes", "opening_hours": "24/7", "name": "EV Charging Station", "_source": "worldwide"}}, {"type": "node", "id": 13689245302, "lat": 35.617262, "lon": 139.777266, "tags": {"amenity": "charging_station", "fee": "yes", "access": "yes", "opening_hours": "24/7", "name": "EV Charging Station", "_source": "worldwide"}}, {"type": "node", "id": 13689247501, "lat": 35.597965, "lon": 139.702835, "tags": {"amenity": "charging_station", "fee": "yes", "access": "yes", "opening_hours": "24/7", "name": "EV Charging Station", "_source": "worldwide"}}, {"type": "node", "id": 13689247502, "lat": 35.642312, "lon": 139.804146, "tags": {"amenity": "charging_station", "fee": "yes", "access": "yes", "opening_hours": "24/7", "name": "EV Charging Station", "_source": "worldwide"}}, {"type": "node", "id": 13689249001, "lat": 35.638123, "lon": 139.7926, "tags": {"amenity": "charging_station", "fee": "yes", "access": "yes", "opening_hours": "24/7", "name": "EV Charging Station", "_source": "worldwide"}}, {"type": "node", "id": 13689250802, "lat": 35.534444, "lon": 139.694709, "tags": {"amenity": "charging_station", "fee": "yes", "access": "yes", "opening_hours": "24/7", "name": "EV Charging Station", "_source": "worldwide"}}, {"type": "node", "id": 13689251001, "lat": 35.763458, "lon": 139.78946, "tags": {"amenity": "charging_station", "fee": "yes", "access": "yes", "opening_hours": "24/7", "name": "EV Charging Station", "_source": "worldwide"}}, {"type": "node", "id": 13689251002, "lat": 35.745381, "lon": 139.525648, "tags": {"amenity": "charging_station", "fee": "yes", "access": "yes", "opening_hours": "24/7", "name": "EV Charging Station", "_source": "worldwide"}}, {"type": "node", "id": 13689252001, "lat": 35.561543, "lon": 139.688267, "tags": {"amenity": "charging_station", "fee": "yes", "access": "yes", "opening_hours": "24/7", "name": "EV Charging Station", "_source": "worldwide"}}, {"type": "node", "id": 13689252002, "lat": 35.587927, "lon": 139.571438, "tags": {"amenity": "charging_station", "fee": "yes", "access": "yes", "opening_hours": "24/7", "name": "EV Charging Station", "_source": "worldwide"}}, {"type": "node", "id": 13689252003, "lat": 35.832434, "lon": 139.735658, "tags": {"amenity": "charging_station", "fee": "yes", "access": "yes", "opening_hours": "24/7", "name": "EV Charging Station", "_source": "worldwide"}}, {"type": "node", "id": 13689252004, "lat": 35.549216, "lon": 139.618143, "tags": {"amenity": "charging_station", "fee": "yes", "access": "yes", "opening_hours": "24/7", "name": "EV Charging Station", "_source": "worldwide"}}, {"type": "node", "id": 13689252005, "lat": 35.810543, "lon": 139.531883, "tags": {"amenity": "charging_station", "fee": "yes", "access": "yes", "opening_hours": "24/7", "name": "EV Charging Station", "_source": "worldwide"}}, {"type": "node", "id": 13689252006, "lat": 35.894235, "lon": 139.732289, "tags": {"amenity": "charging_station", "fee": "yes", "access": "yes", "opening_hours": "24/7", "name": "EV Charging Station", "_source": "worldwide"}}, {"type": "node", "id": 13689257501, "lat": 35.652755, "lon": 139.898559, "tags": {"amenity": "charging_station", "fee": "yes", "access": "yes", "opening_hours": "24/7", "name": "EV Charging Station", "_source": "worldwide"}}, {"type": "node", "id": 13689257502, "lat": 35.676362, "lon": 139.45315, "tags": {"amenity": "charging_station", "fee": "yes", "access": "yes", "opening_hours": "24/7", "name": "EV Charging Station", "_source": "worldwide"}}, {"type": "node", "id": 13689257503, "lat": 35.545516, "lon": 139.525516, "tags": {"amenity": "charging_station", "fee": "yes", "access": "yes", "opening_hours": "24/7", "name": "EV Charging Station", "_source": "worldwide"}}, {"type": "node", "id": 13689260001, "lat": 35.83547, "lon": 139.879006, "tags": {"amenity": "charging_station", "fee": "yes", "access": "yes", "opening_hours": "24/7", "name": "EV Charging Station", "_source": "worldwide"}}, {"type": "node", "id": 13689260002, "lat": 35.890931, "lon": 139.614325, "tags": {"amenity": "charging_station", "fee": "yes", "access": "yes", "opening_hours": "24/7", "name": "EV Charging Station", "_source": "worldwide"}}, {"type": "node", "id": 13689261201, "lat": 35.893553, "lon": 139.607356, "tags": {"amenity": "charging_station", "fee": "yes", "access": "yes", "opening_hours": "24/7", "name": "EV Charging Station", "_source": "worldwide"}}, {"type": "node", "id": 13689261401, "lat": 35.81675, "lon": 139.932394, "tags": {"amenity": "charging_station", "fee": "yes", "access": "yes", "opening_hours": "24/7", "name": "EV Charging Station", "_source": "worldwide"}}, {"type": "node", "id": 13689269501, "lat": 35.457869, "lon": 139.625959, "tags": {"amenity": "charging_station", "fee": "yes", "access": "yes", "opening_hours": "24/7", "name": "EV Charging Station", "_source": "worldwide"}}, {"type": "node", "id": 13689269502, "lat": 35.589087, "lon": 139.350299, "tags": {"amenity": "charging_station", "fee": "yes", "access": "yes", "opening_hours": "24/7", "name": "EV Charging Station", "_source": "worldwide"}}, {"type": "node", "id": 13689273101, "lat": 35.519154, "lon": 139.453576, "tags": {"amenity": "charging_station", "fee": "yes", "access": "yes", "opening_hours": "24/7", "name": "EV Charging Station", "_source": "worldwide"}}, {"type": "node", "id": 13689273801, "lat": 35.426389, "lon": 139.666603, "tags": {"amenity": "charging_station", "fee": "yes", "access": "yes", "opening_hours": "24/7", "name": "EV Charging Station", "_source": "worldwide"}}, {"type": "node", "id": 13689273902, "lat": 35.66974, "lon": 139.331357, "tags": {"amenity": "charging_station", "fee": "yes", "access": "yes", "opening_hours": "24/7", "name": "EV Charging Station", "_source": "worldwide"}}, {"type": "node", "id": 13689278901, "lat": 35.897661, "lon": 139.954713, "tags": {"amenity": "charging_station", "fee": "yes", "access": "yes", "opening_hours": "24/7", "name": "EV Charging Station", "_source": "worldwide"}}, {"type": "node", "id": 13689279401, "lat": 35.435543, "lon": 139.924773, "tags": {"amenity": "charging_station", "fee": "yes", "access": "yes", "opening_hours": "24/7", "name": "EV Charging Station", "_source": "worldwide"}}, {"type": "node", "id": 13689286002, "lat": 35.944335, "lon": 139.385609, "tags": {"amenity": "charging_station", "fee": "yes", "access": "yes", "opening_hours": "24/7", "name": "EV Charging Station", "_source": "worldwide"}}]}