{"id": "-38-148", "latMin": -38, "lonMin": 148, "latMax": -37, "lonMax": 149, "generated": "2026-04-16T18:39:07.185Z", "count": 4, "pois": [{"type": "node", "id": 10062824393, "lat": -37.705732, "lon": 148.455995, "tags": {"amenity": "charging_station", "brand": "Charging the Regions", "operator": "Central Victorian Greenhouse Alliance", "name": "Charging the Regions", "socket:chademo": "1", "capacity": "2", "_source": "worldwide"}}, {"type": "node", "id": 12477914114, "lat": -37.500706, "lon": 148.171568, "tags": {"amenity": "charging_station", "operator": "Chargefox", "name": "Station 7675", "_source": "worldwide"}}, {"type": "node", "id": 12564192749, "lat": -37.498803, "lon": 148.172066, "tags": {"amenity": "charging_station", "operator": "Chargefox", "name": "Chargefox", "socket:chademo": "1", "capacity": "2", "_source": "worldwide"}}, {"type": "node", "id": 13442139297, "lat": -37.070128, "lon": 148.591119, "tags": {"amenity": "charging_station", "operator": "Chargefox", "name": "Chargefox", "capacity": "1", "_source": "worldwide"}}]}