{"id": "49-27", "latMin": 49, "lonMin": 27, "latMax": 50, "lonMax": 28, "generated": "2026-04-16T18:39:08.321Z", "count": 4, "pois": [{"type": "node", "id": 5542788889, "lat": 49.453118, "lon": 27.009815, "tags": {"amenity": "charging_station", "name": "АЕЗС EV-net", "_source": "worldwide"}}, {"type": "node", "id": 5545074321, "lat": 49.442371, "lon": 27.006107, "tags": {"amenity": "charging_station", "operator": "АЕЗС АвтоЕнтерпрайз", "name": "АЕЗС АвтоЕнтерпрайз", "addr:street": "вулиця Марка Кропивницького", "_source": "worldwide"}}, {"type": "node", "id": 6604008070, "lat": 49.076006, "lon": 27.678141, "tags": {"amenity": "charging_station", "fee": "no", "name": "EV Charging Station", "_source": "worldwide"}}, {"type": "node", "id": 6968675607, "lat": 49.443028, "lon": 27.007431, "tags": {"amenity": "charging_station", "name": "EV Charging Station", "_source": "worldwide"}}]}