{"id": "-42-146", "latMin": -42, "lonMin": 146, "latMax": -41, "lonMax": 147, "generated": "2026-04-16T18:39:07.178Z", "count": 12, "pois": [{"type": "node", "id": 3946796253, "lat": -41.218297, "lon": 146.412523, "tags": {"amenity": "charging_station", "fee": "no", "access": "customers", "name": "EV Charging Station", "capacity": "2", "_source": "worldwide"}}, {"type": "node", "id": 5519599141, "lat": -41.382797, "lon": 146.324852, "tags": {"amenity": "charging_station", "fee": "yes", "opening_hours": "24/7", "operator": "Sheffield Visitor Information Centre", "name": "Sheffield Visitor Information Centre", "capacity": "2", "_source": "worldwide"}}, {"type": "node", "id": 6510508421, "lat": -41.527963, "lon": 146.830594, "tags": {"amenity": "charging_station", "fee": "no", "access": "yes", "operator": "Meander Valley Council", "name": "Meander Valley Council", "capacity": "1", "_source": "worldwide"}}, {"type": "node", "id": 7882866714, "lat": -41.523617, "lon": 146.651043, "tags": {"amenity": "charging_station", "fee": "no", "access": "yes", "opening_hours": "24/7", "operator": "Meander Valley Council", "name": "Meander Valley Council", "capacity": "1", "_source": "worldwide"}}, {"type": "node", "id": 8167428500, "lat": -41.177661, "lon": 146.359383, "tags": {"amenity": "charging_station", "fee": "yes", "access": "yes", "opening_hours": "24/7", "brand": "Electric Highway Tasmania", "operator": "Electric Highway Tasmania", "name": "Electric Highway Tasmania", "socket:chademo": "1", "capacity": "3", "_source": "worldwide"}}, {"type": "node", "id": 8678497906, "lat": -41.180002, "lon": 146.367319, "tags": {"amenity": "charging_station", "fee": "yes", "access": "yes", "opening_hours": "24/7", "brand": "Tesla Supercharger", "network": "Supercharger", "operator": "Tesla", "name": "Tesla Supercharger", "socket:tesla_supercharger": "3", "capacity": "3", "_source": "worldwide"}}, {"type": "node", "id": 8864968843, "lat": -41.525806, "lon": 146.845242, "tags": {"amenity": "charging_station", "opening_hours": "24/7", "operator": "Evie Networks", "name": "Evie Networks", "socket:chademo": "1", "capacity": "2", "_source": "worldwide"}}, {"type": "node", "id": 10561388116, "lat": -41.426075, "lon": 146.18007, "tags": {"amenity": "charging_station", "fee": "no", "access": "yes", "name": "EV Charging Station", "capacity": "1", "_source": "worldwide"}}, {"type": "node", "id": 10597363016, "lat": -41.17924, "lon": 146.341445, "tags": {"amenity": "charging_station", "name": "EV Charging Station", "socket:chademo": "1", "capacity": "3", "_source": "worldwide"}}, {"type": "node", "id": 10744595484, "lat": -41.105635, "lon": 146.823424, "tags": {"amenity": "charging_station", "name": "EV Charging Station", "_source": "worldwide"}}, {"type": "node", "id": 12206341968, "lat": -41.299619, "lon": 146.951599, "tags": {"amenity": "charging_station", "fee": "yes", "operator": "Chargefox", "name": "Chargefox", "addr:street": "Main Road", "addr:housenumber": "67", "addr:postcode": "7275", "socket:chademo": "1", "capacity": "2", "_source": "worldwide"}}, {"type": "node", "id": 12435604712, "lat": -41.483845, "lon": 146.597821, "tags": {"amenity": "charging_station", "operator": "NRMA", "name": "NRMA", "socket:chademo": "1", "capacity": "4", "_source": "worldwide"}}]}