{"id": "36--99", "latMin": 36, "lonMin": -99, "latMax": 37, "lonMax": -98, "generated": "2026-04-16T18:39:07.376Z", "count": 1, "pois": [{"type": "node", "id": 13588589473, "lat": 36.167262, "lon": -98.955318, "tags": {"amenity": "charging_station", "fee": "yes", "access": "yes", "opening_hours": "24/7", "brand": "Francis Energy", "network": "Supercharger", "operator": "Tesla", "name": "Francis Energy Supercharger", "addr:street": "US-270", "addr:housenumber": "1098", "addr:postcode": "73663", "addr:city": "Seiling", "addr:country": "US", "socket:type1_combo": "8", "capacity": "16", "_source": "worldwide"}}]}