{"id": "46--119", "latMin": 46, "lonMin": -119, "latMax": 47, "lonMax": -118, "generated": "2026-04-16T18:39:08.114Z", "count": 4, "pois": [{"type": "node", "id": 7004871571, "lat": 46.659124, "lon": -118.861115, "tags": {"amenity": "charging_station", "fee": "yes", "opening_hours": "24/7", "network": "Greenlots", "name": "EV Charging Station", "socket:type1": "1", "capacity": "1", "_source": "worldwide"}}, {"type": "node", "id": 12012924088, "lat": 46.078117, "lon": -118.273793, "tags": {"amenity": "charging_station", "fee": "no", "access": "permissive", "name": "EV Charging Station", "_source": "worldwide"}}, {"type": "node", "id": 12012924089, "lat": 46.068468, "lon": -118.330375, "tags": {"amenity": "charging_station", "fee": "yes", "access": "permissive", "brand": "SemaConnect", "operator": "SemaConnect", "name": "SemaConnect", "_source": "worldwide"}}, {"type": "node", "id": 12012924091, "lat": 46.067946, "lon": -118.341526, "tags": {"amenity": "charging_station", "brand": "Tesla, Inc.", "name": "Tesla Destination Charger", "_source": "worldwide"}}]}