{"id": "-39-178", "latMin": -39, "lonMin": 178, "latMax": -38, "lonMax": 179, "generated": "2026-04-16T18:39:07.182Z", "count": 5, "pois": [{"type": "node", "id": 9956395667, "lat": -38.667624, "lon": 178.027762, "tags": {"amenity": "charging_station", "fee": "yes", "access": "yes", "operator": "ChargeNet NZ", "name": "ChargeNet NZ", "socket:chademo": "1", "capacity": "3", "_source": "worldwide"}}, {"type": "node", "id": 9956479123, "lat": -38.670839, "lon": 178.025453, "tags": {"amenity": "charging_station", "fee": "yes", "access": "yes", "operator": "ChargeNet NZ", "name": "Gisborne (The Warehouse)", "socket:chademo": "1", "capacity": "2", "_source": "worldwide"}}, {"type": "node", "id": 9956497288, "lat": -38.661209, "lon": 178.018161, "tags": {"amenity": "charging_station", "access": "yes", "name": "Countdown Gisborne", "capacity": "4", "_source": "worldwide"}}, {"type": "node", "id": 10078581147, "lat": -38.37384, "lon": 178.296405, "tags": {"amenity": "charging_station", "fee": "yes", "access": "yes", "operator": "ChargeNet NZ", "name": "Monkhouse St Parking/Charging", "socket:chademo": "1", "capacity": "2", "_source": "worldwide"}}, {"type": "node", "id": 13135445917, "lat": -38.130414, "lon": 178.314809, "tags": {"amenity": "charging_station", "name": "EV Charging Station", "_source": "worldwide"}}]}