{"id": "46-28", "latMin": 46, "lonMin": 28, "latMax": 47, "lonMax": 29, "generated": "2026-04-16T18:39:08.132Z", "count": 20, "pois": [{"type": "node", "id": 7466815319, "lat": 46.526548, "lon": 28.781051, "tags": {"amenity": "charging_station", "name": "EV Charging Station", "_source": "worldwide"}}, {"type": "node", "id": 7466815320, "lat": 46.527281, "lon": 28.780509, "tags": {"amenity": "charging_station", "name": "EV Charging Station", "_source": "worldwide"}}, {"type": "node", "id": 7466815321, "lat": 46.485495, "lon": 28.27402, "tags": {"amenity": "charging_station", "name": "EV Charging Station", "_source": "worldwide"}}, {"type": "node", "id": 7466815323, "lat": 46.306694, "lon": 28.659078, "tags": {"amenity": "charging_station", "name": "EV Charging Station", "_source": "worldwide"}}, {"type": "node", "id": 7466815324, "lat": 46.093255, "lon": 28.595132, "tags": {"amenity": "charging_station", "name": "EV Charging Station", "_source": "worldwide"}}, {"type": "node", "id": 7466815325, "lat": 46.063302, "lon": 28.814311, "tags": {"amenity": "charging_station", "name": "EV Charging Station", "_source": "worldwide"}}, {"type": "node", "id": 7466815331, "lat": 46.795311, "lon": 28.167941, "tags": {"amenity": "charging_station", "name": "EV Charging Station", "_source": "worldwide"}}, {"type": "node", "id": 7466815332, "lat": 46.828958, "lon": 28.196793, "tags": {"amenity": "charging_station", "name": "EV Charging Station", "_source": "worldwide"}}, {"type": "node", "id": 7466815333, "lat": 46.995195, "lon": 28.666387, "tags": {"amenity": "charging_station", "name": "EV Charging Station", "_source": "worldwide"}}, {"type": "node", "id": 7466815334, "lat": 46.991621, "lon": 28.787324, "tags": {"amenity": "charging_station", "name": "EV Charging Station", "_source": "worldwide"}}, {"type": "node", "id": 7466815335, "lat": 46.993919, "lon": 28.792879, "tags": {"amenity": "charging_station", "name": "EV Charging Station", "_source": "worldwide"}}, {"type": "node", "id": 7466815336, "lat": 46.965844, "lon": 28.890124, "tags": {"amenity": "charging_station", "name": "EV Charging Station", "_source": "worldwide"}}, {"type": "node", "id": 7466815337, "lat": 46.973563, "lon": 28.847499, "tags": {"amenity": "charging_station", "name": "EV Charging Station", "_source": "worldwide"}}, {"type": "node", "id": 7466815338, "lat": 46.980511, "lon": 28.89122, "tags": {"amenity": "charging_station", "name": "EV Charging Station", "_source": "worldwide"}}, {"type": "node", "id": 7466815340, "lat": 46.987154, "lon": 28.915381, "tags": {"amenity": "charging_station", "name": "EV Charging Station", "_source": "worldwide"}}, {"type": "node", "id": 7466815341, "lat": 46.995203, "lon": 28.891557, "tags": {"amenity": "charging_station", "name": "Stația de Încărcare „Green'Up\"", "_source": "worldwide"}}, {"type": "node", "id": 11106971955, "lat": 46.953478, "lon": 28.763944, "tags": {"amenity": "charging_station", "name": "EcoFactor Charging Station", "_source": "worldwide"}}, {"type": "node", "id": 11106981795, "lat": 46.954278, "lon": 28.769795, "tags": {"amenity": "charging_station", "name": "EV Charging Station", "_source": "worldwide"}}, {"type": "node", "id": 12566095931, "lat": 46.990035, "lon": 28.860707, "tags": {"amenity": "charging_station", "brand": "Charging Station Kaufland", "operator": "Kaufland", "name": "Charging Station Kaufland", "_source": "worldwide"}}, {"type": "node", "id": 12879477501, "lat": 46.990631, "lon": 28.859317, "tags": {"amenity": "charging_station", "opening_hours": "24/7", "operator": "Plug2Go", "name": "Plug2Go", "addr:street": "Bulevardul Decebal", "addr:country": "MD", "_source": "worldwide"}}]}