{"id": "28--83", "latMin": 28, "lonMin": -83, "latMax": 29, "lonMax": -82, "generated": "2026-04-16T18:39:07.258Z", "count": 36, "pois": [{"type": "node", "id": 1577184743, "lat": 28.064101, "lon": -82.412444, "tags": {"amenity": "charging_station", "name": "EV Charging Station", "_source": "worldwide"}}, {"type": "node", "id": 3683018016, "lat": 28.036553, "lon": -82.661898, "tags": {"amenity": "charging_station", "fee": "yes", "opening_hours": "24/7", "brand": "ChargePoint", "operator": "ChargePoint", "name": "ChargePoint", "socket:type1": "1", "capacity": "2", "_source": "worldwide"}}, {"type": "node", "id": 3683047241, "lat": 28.035954, "lon": -82.6603, "tags": {"amenity": "charging_station", "fee": "yes", "opening_hours": "24/7", "brand": "ChargePoint", "operator": "ChargePoint", "name": "ChargePoint", "socket:type1": "1", "capacity": "2", "_source": "worldwide"}}, {"type": "node", "id": 3683052924, "lat": 28.034117, "lon": -82.656996, "tags": {"amenity": "charging_station", "fee": "yes", "opening_hours": "24/7", "brand": "ChargePoint", "operator": "ChargePoint", "name": "ChargePoint", "socket:type1": "1", "capacity": "2", "_source": "worldwide"}}, {"type": "node", "id": 3683057590, "lat": 28.034351, "lon": -82.659242, "tags": {"amenity": "charging_station", "fee": "yes", "opening_hours": "24/7", "brand": "ChargePoint", "operator": "ChargePoint", "name": "ChargePoint", "socket:type1": "1", "capacity": "2", "_source": "worldwide"}}, {"type": "node", "id": 3683084334, "lat": 28.237243, "lon": -82.726541, "tags": {"amenity": "charging_station", "fee": "yes", "opening_hours": "24/7", "name": "Greenlots", "socket:chademo": "1", "socket:type1_combo": "1", "capacity": "2", "_source": "worldwide"}}, {"type": "node", "id": 4028057214, "lat": 28.058823, "lon": -82.417254, "tags": {"amenity": "charging_station", "name": "EV Charging Station", "_source": "worldwide"}}, {"type": "node", "id": 4414178992, "lat": 28.050154, "lon": -82.414488, "tags": {"amenity": "charging_station", "name": "EV Charging Station", "_source": "worldwide"}}, {"type": "node", "id": 4414178993, "lat": 28.050964, "lon": -82.394127, "tags": {"amenity": "charging_station", "name": "EV Charging Station", "_source": "worldwide"}}, {"type": "node", "id": 4414178994, "lat": 28.049639, "lon": -82.458321, "tags": {"amenity": "charging_station", "name": "EV Charging Station", "_source": "worldwide"}}, {"type": "node", "id": 4414245590, "lat": 28.055817, "lon": -82.408233, "tags": {"amenity": "charging_station", "name": "EV Charging Station", "_source": "worldwide"}}, {"type": "node", "id": 4420318489, "lat": 28.09169, "lon": -82.403516, "tags": {"amenity": "charging_station", "name": "EV Charging Station", "_source": "worldwide"}}, {"type": "node", "id": 5387549693, "lat": 28.035691, "lon": -82.657394, "tags": {"amenity": "charging_station", "opening_hours": "24/7", "brand": "ChargePoint", "operator": "ChargePoint", "name": "ChargePoint", "_source": "worldwide"}}, {"type": "node", "id": 6049212075, "lat": 28.016883, "lon": -82.736096, "tags": {"amenity": "charging_station", "fee": "no", "authentication": "no", "operator": "Whole Foods", "name": "Whole Foods", "socket:type1": "2", "capacity": "2", "_source": "worldwide"}}, {"type": "node", "id": 7265083537, "lat": 28.191712, "lon": -82.392599, "tags": {"amenity": "charging_station", "fee": "yes", "access": "yes", "brand": "ChargePoint", "operator": "ChargePoint", "name": "ChargePoint", "socket:type1": "1", "capacity": "1", "_source": "worldwide"}}, {"type": "node", "id": 7534030739, "lat": 28.0133, "lon": -82.73624, "tags": {"amenity": "charging_station", "fee": "yes", "access": "yes", "opening_hours": "24/7", "brand": "Tesla Supercharger", "network": "Supercharger", "operator": "Tesla, Inc.", "name": "Tesla Supercharger", "addr:street": "US Highway 19", "addr:housenumber": "26508", "addr:postcode": "33761", "addr:city": "Clearwater", "addr:country": "US", "capacity": "8", "_source": "worldwide"}}, {"type": "node", "id": 9839070596, "lat": 28.08855, "lon": -82.4521, "tags": {"amenity": "charging_station", "fee": "yes", "access": "yes", "opening_hours": "24/7", "brand": "Tesla Supercharger", "network": "Supercharger", "operator": "Tesla, Inc.", "name": "Tampa - East Bearss Ave Supercharger", "addr:street": "East Bearss Avenue", "addr:housenumber": "804", "addr:postcode": "33613", "addr:city": "Tampa", "addr:country": "US", "capacity": "8", "_source": "worldwide"}}, {"type": "node", "id": 9839073518, "lat": 28.18981, "lon": -82.40008, "tags": {"amenity": "charging_station", "fee": "yes", "access": "yes", "opening_hours": "24/7", "brand": "Tesla Supercharger", "network": "Supercharger", "operator": "Tesla", "name": "Land O’ Lakes Supercharger", "addr:street": "Maren Way", "addr:housenumber": "25155", "addr:postcode": "34639", "addr:city": "Land O’ Lakes", "addr:country": "US", "capacity": "8", "_source": "worldwide"}}, {"type": "node", "id": 11639916184, "lat": 28.216332, "lon": -82.738451, "tags": {"amenity": "charging_station", "name": "EV Charging Station", "_source": "worldwide"}}, {"type": "node", "id": 11646603055, "lat": 28.21802, "lon": -82.7362, "tags": {"amenity": "charging_station", "fee": "yes", "access": "yes", "opening_hours": "24/7", "brand": "Tesla Supercharger", "network": "Supercharger", "operator": "Tesla, Inc.", "name": "New Port Richey Supercharger", "addr:street": "US-19", "addr:housenumber": "4026", "addr:postcode": "34652", "addr:city": "New Port Richey", "addr:country": "US", "capacity": "8", "_source": "worldwide"}}, {"type": "node", "id": 11646603065, "lat": 28.13663, "lon": -82.75673, "tags": {"amenity": "charging_station", "fee": "yes", "access": "yes", "opening_hours": "24/7", "brand": "Tesla Supercharger", "network": "Supercharger", "operator": "Tesla, Inc.", "name": "Tesla Supercharger", "addr:street": "South Pinellas Avenue", "addr:housenumber": "1171", "addr:postcode": "34689", "addr:city": "Tarpon Springs", "addr:country": "US", "capacity": "12", "_source": "worldwide"}}, {"type": "node", "id": 12241900496, "lat": 28.52269, "lon": -82.22998, "tags": {"amenity": "charging_station", "fee": "yes", "access": "yes", "opening_hours": "24/7", "brand": "Tesla Supercharger", "network": "Supercharger", "operator": "Tesla", "name": "Brooksville Supercharger", "addr:street": "Cortez Boulevard", "addr:housenumber": "31100", "addr:postcode": "34602", "addr:city": "Brooksville", "addr:country": "US", "capacity": "12", "_source": "worldwide"}}, {"type": "node", "id": 12244865067, "lat": 28.02605, "lon": -82.15171, "tags": {"amenity": "charging_station", "fee": "yes", "access": "yes", "opening_hours": "24/7", "brand": "Tesla Supercharger", "network": "Supercharger", "operator": "Tesla, Inc.", "name": "Plant City Supercharger", "addr:street": "Thonotosassa Road", "addr:housenumber": "2705", "addr:postcode": "33563", "addr:city": "Plant City", "addr:country": "US", "capacity": "8", "_source": "worldwide"}}, {"type": "node", "id": 12877363075, "lat": 28.666894, "lon": -82.13836, "tags": {"amenity": "charging_station", "operator": "Electrify America", "name": "Electrify America", "_source": "worldwide"}}, {"type": "node", "id": 12877363076, "lat": 28.87483, "lon": -82.579353, "tags": {"amenity": "charging_station", "fee": "yes", "access": "yes", "operator": "Duke Energy", "name": "Greenlots", "_source": "worldwide"}}, {"type": "node", "id": 12878074056, "lat": 28.13083, "lon": -82.366382, "tags": {"amenity": "charging_station", "fee": "yes", "opening_hours": "24/7", "operator": "Electrify America", "name": "Electrify America", "socket:type1_combo": "2", "capacity": "2", "_source": "worldwide"}}, {"type": "node", "id": 12878074057, "lat": 28.19287, "lon": -82.391527, "tags": {"amenity": "charging_station", "fee": "yes", "opening_hours": "24/7", "brand": "Electrify America", "operator": "Electrify America", "name": "Electrify America", "_source": "worldwide"}}, {"type": "node", "id": 12878074058, "lat": 28.250574, "lon": -82.720495, "tags": {"amenity": "charging_station", "fee": "yes", "access": "yes", "brand": "EV Connect -CCS connectors", "network": "EV connect", "operator": "Duke energy", "name": "EV Connect -CCS connectors", "_source": "worldwide"}}, {"type": "node", "id": 12879217223, "lat": 28.039, "lon": -82.46, "tags": {"amenity": "charging_station", "opening_hours": "24/7", "brand": "ChargePoint", "network": "ChargePoint", "name": "ChargePoint", "addr:street": "North Florida Avenue", "addr:housenumber": "9560", "addr:postcode": "33612", "addr:city": "Tampa", "addr:country": "US", "socket:type1_combo": "4", "capacity": "4", "_source": "worldwide"}}, {"type": "node", "id": 12923488226, "lat": 28.53474, "lon": -82.50792, "tags": {"amenity": "charging_station", "fee": "yes", "access": "yes", "opening_hours": "24/7", "brand": "Tesla Supercharger", "network": "Supercharger", "operator": "Tesla", "name": "Tesla Supercharger", "addr:street": "Cortez Boulevard", "addr:housenumber": "13173", "addr:postcode": "33613", "addr:city": "Brooksville", "addr:country": "US", "capacity": "12", "_source": "worldwide"}}, {"type": "node", "id": 12923488239, "lat": 28.19007, "lon": -82.61618, "tags": {"amenity": "charging_station", "fee": "yes", "access": "yes", "opening_hours": "24/7", "brand": "Tesla Supercharger", "network": "Supercharger", "operator": "Tesla, Inc.", "name": "Odessa Supercharger", "addr:street": "FL-54", "addr:housenumber": "12048", "addr:postcode": "33556", "addr:city": "Odessa", "addr:country": "US", "capacity": "8", "_source": "worldwide"}}, {"type": "node", "id": 12923488261, "lat": 28.89956, "lon": -82.58678, "tags": {"amenity": "charging_station", "fee": "yes", "access": "yes", "opening_hours": "24/7", "brand": "Tesla Supercharger", "network": "Supercharger", "operator": "Tesla, Inc.", "name": "Crystal River Supercharger", "addr:street": "US-19", "addr:housenumber": "509", "addr:postcode": "34429", "addr:city": "Crystal River", "addr:country": "US", "capacity": "8", "_source": "worldwide"}}, {"type": "node", "id": 13319861746, "lat": 28.192867, "lon": -82.539173, "tags": {"amenity": "charging_station", "fee": "yes", "access": "yes", "opening_hours": "24/7", "brand": "Suncoast", "network": "Supercharger", "operator": "Tesla", "name": "Suncoast Supercharger", "addr:street": "Focus Loop", "addr:housenumber": "16954", "addr:postcode": "34638", "addr:city": "Land O' Lakes", "addr:country": "US", "socket:type1_combo": "8", "capacity": "16", "_source": "worldwide"}}, {"type": "node", "id": 13351548013, "lat": 28.188702, "lon": -82.350538, "tags": {"amenity": "charging_station", "opening_hours": "24/7", "brand": "EVgo", "operator": "EVgo", "name": "EVgo", "_source": "worldwide"}}, {"type": "node", "id": 13667926104, "lat": 28.204281, "lon": -82.665867, "tags": {"amenity": "charging_station", "fee": "yes", "access": "yes", "opening_hours": "24/7", "brand": "Tesla Supercharger", "network": "Supercharger", "operator": "Tesla", "name": "Trinity Supercharger", "_source": "worldwide"}}, {"type": "node", "id": 13667926203, "lat": 28.23881, "lon": -82.364813, "tags": {"amenity": "charging_station", "fee": "yes", "access": "yes", "opening_hours": "24/7", "brand": "Tesla Supercharger", "network": "Supercharger", "operator": "Tesla", "name": "Wesley Chapel Supercharger", "_source": "worldwide"}}]}