{"id": "23-116", "latMin": 23, "lonMin": 116, "latMax": 24, "lonMax": 117, "generated": "2026-04-16T18:39:07.245Z", "count": 15, "pois": [{"type": "node", "id": 11708168458, "lat": 23.955962, "lon": 116.200351, "tags": {"amenity": "charging_station", "name": "EV Charging Station", "_source": "worldwide"}}, {"type": "node", "id": 13016913566, "lat": 23.433676, "lon": 116.942126, "tags": {"amenity": "charging_station", "name": "南方电网汽车充电站(汕头市南澳供电局长山尾充公共电站)", "_source": "worldwide"}}, {"type": "node", "id": 13019470031, "lat": 23.40207, "lon": 116.630003, "tags": {"amenity": "charging_station", "access": "private", "name": "EV Charging Station", "_source": "worldwide"}}, {"type": "node", "id": 13019470032, "lat": 23.403437, "lon": 116.629977, "tags": {"amenity": "charging_station", "access": "private", "name": "EV Charging Station", "_source": "worldwide"}}, {"type": "node", "id": 13019470033, "lat": 23.403633, "lon": 116.629101, "tags": {"amenity": "charging_station", "access": "private", "name": "EV Charging Station", "_source": "worldwide"}}, {"type": "node", "id": 13019470034, "lat": 23.405338, "lon": 116.630092, "tags": {"amenity": "charging_station", "access": "private", "name": "EV Charging Station", "_source": "worldwide"}}, {"type": "node", "id": 13019470035, "lat": 23.404688, "lon": 116.63109, "tags": {"amenity": "charging_station", "access": "private", "name": "EV Charging Station", "_source": "worldwide"}}, {"type": "node", "id": 13019470038, "lat": 23.406047, "lon": 116.629436, "tags": {"amenity": "charging_station", "access": "private", "name": "EV Charging Station", "_source": "worldwide"}}, {"type": "node", "id": 13019470039, "lat": 23.405729, "lon": 116.629319, "tags": {"amenity": "charging_station", "access": "private", "name": "EV Charging Station", "_source": "worldwide"}}, {"type": "node", "id": 13019470040, "lat": 23.404561, "lon": 116.627894, "tags": {"amenity": "charging_station", "access": "private", "name": "EV Charging Station", "_source": "worldwide"}}, {"type": "node", "id": 13019470041, "lat": 23.405064, "lon": 116.628051, "tags": {"amenity": "charging_station", "access": "private", "name": "EV Charging Station", "_source": "worldwide"}}, {"type": "node", "id": 13019470042, "lat": 23.405247, "lon": 116.627146, "tags": {"amenity": "charging_station", "access": "private", "name": "EV Charging Station", "_source": "worldwide"}}, {"type": "node", "id": 13019470043, "lat": 23.405149, "lon": 116.627613, "tags": {"amenity": "charging_station", "access": "private", "name": "EV Charging Station", "_source": "worldwide"}}, {"type": "node", "id": 13019470045, "lat": 23.404707, "lon": 116.627474, "tags": {"amenity": "charging_station", "access": "private", "name": "EV Charging Station", "_source": "worldwide"}}, {"type": "node", "id": 13019470059, "lat": 23.404627, "lon": 116.634026, "tags": {"amenity": "charging_station", "access": "private", "name": "EV Charging Station", "_source": "worldwide"}}]}