{"id": "59-30", "latMin": 59, "lonMin": 30, "latMax": 60, "lonMax": 31, "generated": "2026-04-16T18:39:08.786Z", "count": 81, "pois": [{"type": "node", "id": 5579009140, "lat": 59.905767, "lon": 30.306652, "tags": {"amenity": "charging_station", "fee": "no", "opening_hours": "closed", "operator": "ПАО \"Ленэнерго\"", "name": "ПАО \"Ленэнерго\"", "capacity": "2", "_source": "worldwide"}}, {"type": "node", "id": 5610830025, "lat": 59.858103, "lon": 30.246863, "tags": {"amenity": "charging_station", "fee": "no", "opening_hours": "24/7", "operator": "ПАО \"Ленэнерго\"", "name": "ПАО \"Ленэнерго\"", "capacity": "2", "_source": "worldwide"}}, {"type": "node", "id": 5650899736, "lat": 59.799061, "lon": 30.274984, "tags": {"amenity": "charging_station", "fee": "no", "opening_hours": "24/7", "operator": "ПАО \"Ленэнерго\"", "name": "ПАО \"Ленэнерго\"", "socket:schuko": "1", "capacity": "2", "_source": "worldwide"}}, {"type": "node", "id": 5650899737, "lat": 59.835665, "lon": 30.430385, "tags": {"amenity": "charging_station", "fee": "no", "opening_hours": "24/7", "operator": "ПАО «Ленэнерго»", "name": "ПАО «Ленэнерго»", "socket:chademo": "1", "capacity": "3", "_source": "worldwide"}}, {"type": "node", "id": 5650899744, "lat": 59.908313, "lon": 30.327723, "tags": {"amenity": "charging_station", "fee": "no", "opening_hours": "24/7", "operator": "ПАО \"Ленэнерго\"", "name": "ПАО \"Ленэнерго\"", "socket:chademo": "1", "capacity": "3", "_source": "worldwide"}}, {"type": "node", "id": 5650899745, "lat": 59.928469, "lon": 30.453007, "tags": {"amenity": "charging_station", "fee": "no", "opening_hours": "24/7", "operator": "ПАО \"Ленэнерго\"", "name": "ПАО \"Ленэнерго\"", "socket:chademo": "1", "capacity": "3", "_source": "worldwide"}}, {"type": "node", "id": 5650899746, "lat": 59.89837, "lon": 30.422824, "tags": {"amenity": "charging_station", "fee": "no", "opening_hours": "24/7", "operator": "ПАО \"Ленэнерго\"", "name": "ПАО \"Ленэнерго\"", "socket:chademo": "1", "capacity": "3", "_source": "worldwide"}}, {"type": "node", "id": 5650899747, "lat": 59.92989, "lon": 30.258201, "tags": {"amenity": "charging_station", "fee": "no", "opening_hours": "24/7", "operator": "ПАО \"Ленэнерго\"", "name": "ПАО \"Ленэнерго\"", "socket:chademo": "1", "capacity": "3", "_source": "worldwide"}}, {"type": "node", "id": 5650899748, "lat": 59.847644, "lon": 30.297309, "tags": {"amenity": "charging_station", "fee": "no", "opening_hours": "24/7", "operator": "ПАО \"Ленэнерго\"", "name": "ПАО \"Ленэнерго\"", "socket:chademo": "1", "capacity": "3", "_source": "worldwide"}}, {"type": "node", "id": 5650899749, "lat": 59.978007, "lon": 30.423535, "tags": {"amenity": "charging_station", "fee": "no", "opening_hours": "24/7", "operator": "ПАО \"Ленэнерго\"", "name": "ПАО \"Ленэнерго\"", "socket:chademo": "1", "capacity": "3", "_source": "worldwide"}}, {"type": "node", "id": 5650899751, "lat": 59.762838, "lon": 30.35439, "tags": {"amenity": "charging_station", "fee": "no", "opening_hours": "24/7", "operator": "ПАО \"Ленэнерго\"", "name": "ПАО \"Ленэнерго\"", "socket:chademo": "1", "capacity": "3", "_source": "worldwide"}}, {"type": "node", "id": 5650899754, "lat": 59.970089, "lon": 30.229126, "tags": {"amenity": "charging_station", "fee": "no", "opening_hours": "closed", "operator": "ПАО \"Ленэнерго\"", "name": "ПАО \"Ленэнерго\"", "socket:chademo": "1", "capacity": "2", "_source": "worldwide"}}, {"type": "node", "id": 5650899755, "lat": 59.835412, "lon": 30.168046, "tags": {"amenity": "charging_station", "fee": "no", "opening_hours": "24/7", "operator": "ПАО \"Ленэнерго\"", "name": "ПАО \"Ленэнерго\"", "socket:chademo": "1", "capacity": "1", "_source": "worldwide"}}, {"type": "node", "id": 5650899760, "lat": 59.974338, "lon": 30.248831, "tags": {"amenity": "charging_station", "fee": "no", "opening_hours": "24/7", "operator": "ПАО \"Ленэнерго\"", "name": "ПАО \"Ленэнерго\"", "socket:chademo": "1", "capacity": "3", "_source": "worldwide"}}, {"type": "node", "id": 5650899761, "lat": 59.990136, "lon": 30.204218, "tags": {"amenity": "charging_station", "fee": "no", "opening_hours": "24/7", "operator": "ПАО \"Ленэнерго\"", "name": "ПАО \"Ленэнерго\"", "socket:chademo": "1", "capacity": "3", "_source": "worldwide"}}, {"type": "node", "id": 5650899762, "lat": 59.928396, "lon": 30.360059, "tags": {"amenity": "charging_station", "fee": "no", "opening_hours": "closed", "operator": "ПАО \"Ленэнерго\"", "name": "ПАО \"Ленэнерго\"", "socket:schuko": "1", "capacity": "2", "_source": "worldwide"}}, {"type": "node", "id": 5650899764, "lat": 59.894222, "lon": 30.511389, "tags": {"amenity": "charging_station", "fee": "no", "opening_hours": "closed", "operator": "ПАО \"Ленэнерго\"", "name": "ПАО \"Ленэнерго\"", "capacity": "2", "_source": "worldwide"}}, {"type": "node", "id": 5650899767, "lat": 59.93778, "lon": 30.385713, "tags": {"amenity": "charging_station", "fee": "no", "opening_hours": "closed", "operator": "ПАО \"Ленэнерго\"", "name": "ПАО \"Ленэнерго\"", "socket:chademo": "1", "capacity": "3", "_source": "worldwide"}}, {"type": "node", "id": 5650899768, "lat": 59.913499, "lon": 30.375348, "tags": {"amenity": "charging_station", "fee": "no", "opening_hours": "24/7", "operator": "ПАО \"Ленэнерго\"", "name": "ПАО \"Ленэнерго\"", "capacity": "2", "_source": "worldwide"}}, {"type": "node", "id": 5650899773, "lat": 59.805088, "lon": 30.322463, "tags": {"amenity": "charging_station", "fee": "no", "opening_hours": "24/7", "operator": "ПАО \"Ленэнерго\"", "name": "ПАО \"Ленэнерго\"", "socket:chademo": "1", "capacity": "3", "_source": "worldwide"}}, {"type": "node", "id": 6347892243, "lat": 59.901308, "lon": 30.270837, "tags": {"amenity": "charging_station", "operator": "ПАО «Россети Ленэнерго»", "name": "ПАО «Россети Ленэнерго»", "_source": "worldwide"}}, {"type": "node", "id": 6355999758, "lat": 59.931759, "lon": 30.259351, "tags": {"amenity": "charging_station", "operator": "Россети", "name": "Россети", "_source": "worldwide"}}, {"type": "node", "id": 6581200985, "lat": 59.887403, "lon": 30.451818, "tags": {"amenity": "charging_station", "name": "EV Charging Station", "_source": "worldwide"}}, {"type": "node", "id": 6846863885, "lat": 59.93537, "lon": 30.39266, "tags": {"amenity": "charging_station", "operator": "Технополис", "name": "Технополис", "_source": "worldwide"}}, {"type": "node", "id": 7001159585, "lat": 59.863459, "lon": 30.502706, "tags": {"amenity": "charging_station", "name": "EV Charging Station", "_source": "worldwide"}}, {"type": "node", "id": 7683989815, "lat": 59.929126, "lon": 30.386838, "tags": {"amenity": "charging_station", "name": "EV Charging Station", "_source": "worldwide"}}, {"type": "node", "id": 7725178584, "lat": 59.983937, "lon": 30.235749, "tags": {"amenity": "charging_station", "name": "EVlink", "capacity": "1", "_source": "worldwide"}}, {"type": "node", "id": 8252151699, "lat": 59.703537, "lon": 30.550707, "tags": {"amenity": "charging_station", "fee": "no", "opening_hours": "24/7", "operator": "ПАО \"Ленэнерго\"", "name": "ПАО \"Ленэнерго\"", "_source": "worldwide"}}, {"type": "node", "id": 8335801994, "lat": 59.700855, "lon": 30.553756, "tags": {"amenity": "charging_station", "fee": "no", "opening_hours": "24/7", "operator": "ПАО \"Ленэнерго\"", "name": "ПАО \"Ленэнерго\"", "_source": "worldwide"}}, {"type": "node", "id": 8507672198, "lat": 59.991457, "lon": 30.255536, "tags": {"amenity": "charging_station", "fee": "yes", "access": "yes", "name": "EV Charging Station", "_source": "worldwide"}}, {"type": "node", "id": 8887460383, "lat": 59.969531, "lon": 30.317356, "tags": {"amenity": "charging_station", "access": "yes", "operator": "Touch", "name": "Touch", "_source": "worldwide"}}, {"type": "node", "id": 8905524047, "lat": 59.913159, "lon": 30.375403, "tags": {"amenity": "charging_station", "name": "EV Charging Station", "_source": "worldwide"}}, {"type": "node", "id": 9931511878, "lat": 59.806497, "lon": 30.160235, "tags": {"amenity": "charging_station", "fee": "yes", "access": "yes", "operator": "ПАО «Россети Ленэнерго»", "name": "ПАО «Россети Ленэнерго»", "_source": "worldwide"}}, {"type": "node", "id": 10095620953, "lat": 59.90354, "lon": 30.399373, "tags": {"amenity": "charging_station", "brand": "EnelX", "name": "EnelX", "_source": "worldwide"}}, {"type": "node", "id": 10881076534, "lat": 59.793512, "lon": 30.144624, "tags": {"amenity": "charging_station", "fee": "yes", "access": "yes", "opening_hours": "24/7", "brand": "Punkt E", "network": "Punkt E", "operator": "ООО «Ток Бокс Мобилити»", "name": "Punkt E", "_source": "worldwide"}}, {"type": "node", "id": 10887356497, "lat": 59.849994, "lon": 30.146042, "tags": {"amenity": "charging_station", "fee": "yes", "opening_hours": "24/7", "operator": "Россети", "name": "Россети", "socket:chademo": "1", "capacity": "3", "_source": "worldwide"}}, {"type": "node", "id": 11169740741, "lat": 59.740226, "lon": 30.582612, "tags": {"amenity": "charging_station", "access": "yes", "brand": "Ленэнерго", "operator": "Ленэнерго", "name": "Ленэнерго", "_source": "worldwide"}}, {"type": "node", "id": 11742172025, "lat": 59.851028, "lon": 30.477599, "tags": {"amenity": "charging_station", "fee": "yes", "access": "yes", "opening_hours": "24/7", "brand": "Punkt E", "network": "Punkt E", "operator": "ООО «Пункт Е»", "name": "Punkt E", "_source": "worldwide"}}, {"type": "node", "id": 11742961891, "lat": 59.832425, "lon": 30.195101, "tags": {"amenity": "charging_station", "fee": "yes", "access": "yes", "opening_hours": "24/7", "brand": "Punkt E", "network": "Punkt E", "operator": "ООО «Пункт Е»", "name": "Punkt E", "_source": "worldwide"}}, {"type": "node", "id": 11748745573, "lat": 59.810603, "lon": 30.077475, "tags": {"amenity": "charging_station", "access": "yes", "operator": "EV-Time", "name": "EV-Time", "_source": "worldwide"}}, {"type": "node", "id": 11944621569, "lat": 59.893842, "lon": 30.463848, "tags": {"amenity": "charging_station", "fee": "yes", "brand": "Яндекс Заправки", "operator": "Яндекс", "name": "Яндекс Заправки", "_source": "worldwide"}}, {"type": "node", "id": 11949853244, "lat": 59.944161, "lon": 30.227749, "tags": {"amenity": "charging_station", "fee": "yes", "brand": "Punkt E", "name": "Punkt E", "_source": "worldwide"}}, {"type": "node", "id": 11949882839, "lat": 59.956752, "lon": 30.243289, "tags": {"amenity": "charging_station", "fee": "yes", "brand": "силовые машины", "name": "силовые машины", "_source": "worldwide"}}, {"type": "node", "id": 11954862164, "lat": 59.953435, "lon": 30.259938, "tags": {"amenity": "charging_station", "fee": "yes", "name": "EV Charging Station", "_source": "worldwide"}}, {"type": "node", "id": 11966501959, "lat": 59.816194, "lon": 30.354709, "tags": {"amenity": "charging_station", "name": "EVlink", "_source": "worldwide"}}, {"type": "node", "id": 11967492455, "lat": 59.955807, "lon": 30.247323, "tags": {"amenity": "charging_station", "fee": "yes", "brand": "Punkt E", "name": "Punkt E", "_source": "worldwide"}}, {"type": "node", "id": 12010629095, "lat": 59.942441, "lon": 30.39673, "tags": {"amenity": "charging_station", "name": "EV Charging Station", "_source": "worldwide"}}, {"type": "node", "id": 12066533670, "lat": 59.90725, "lon": 30.306699, "tags": {"amenity": "charging_station", "brand": "Ленэнерго", "operator": "Ленэнерго", "name": "Ленэнерго", "_source": "worldwide"}}, {"type": "node", "id": 12068577214, "lat": 59.984654, "lon": 30.27252, "tags": {"amenity": "charging_station", "brand": "Яндекс.Заправки", "name": "Яндекс.Заправки", "_source": "worldwide"}}, {"type": "node", "id": 12248690717, "lat": 59.702791, "lon": 30.381088, "tags": {"amenity": "charging_station", "operator": "Россети", "name": "Россети", "_source": "worldwide"}}, {"type": "node", "id": 12309353205, "lat": 59.867834, "lon": 30.438232, "tags": {"amenity": "charging_station", "name": "EV Charging Station", "_source": "worldwide"}}, {"type": "node", "id": 12371650221, "lat": 59.734999, "lon": 30.612981, "tags": {"amenity": "charging_station", "opening_hours": "Mo-Su 03:00-20:00", "brand": "Punkt E", "name": "Punkt E", "_source": "worldwide"}}, {"type": "node", "id": 12378557743, "lat": 59.738248, "lon": 30.620793, "tags": {"amenity": "charging_station", "fee": "yes", "brand": "Атомэнерго", "name": "Атомэнерго", "_source": "worldwide"}}, {"type": "node", "id": 12402792086, "lat": 59.730097, "lon": 30.082165, "tags": {"amenity": "charging_station", "name": "EV Charging Station", "socket:chademo": "1", "capacity": "2", "_source": "worldwide"}}, {"type": "node", "id": 12410030052, "lat": 59.747534, "lon": 30.567449, "tags": {"amenity": "charging_station", "fee": "yes", "brand": "Атомэнерго", "name": "Атомэнерго", "_source": "worldwide"}}, {"type": "node", "id": 12426313256, "lat": 59.711412, "lon": 30.436434, "tags": {"amenity": "charging_station", "operator": "IT Charge", "name": "IT Charge", "_source": "worldwide"}}, {"type": "node", "id": 12449975861, "lat": 59.961318, "lon": 30.404773, "tags": {"amenity": "charging_station", "opening_hours": "24/7", "brand": "Яндекс Заправки", "name": "Яндекс Заправки", "_source": "worldwide"}}, {"type": "node", "id": 12464799465, "lat": 59.744793, "lon": 30.562637, "tags": {"amenity": "charging_station", "fee": "yes", "brand": "Атомэнерго", "name": "Атомэнерго", "_source": "worldwide"}}, {"type": "node", "id": 12464799466, "lat": 59.7365, "lon": 30.581149, "tags": {"amenity": "charging_station", "fee": "yes", "brand": "Атомэнерго", "name": "Атомэнерго", "_source": "worldwide"}}, {"type": "node", "id": 12464799467, "lat": 59.731713, "lon": 30.614534, "tags": {"amenity": "charging_station", "fee": "yes", "brand": "Evtime", "name": "Evtime", "_source": "worldwide"}}, {"type": "node", "id": 12475804527, "lat": 59.716517, "lon": 30.079232, "tags": {"amenity": "charging_station", "name": "EV Charging Station", "_source": "worldwide"}}, {"type": "node", "id": 12475900137, "lat": 59.854278, "lon": 30.21554, "tags": {"amenity": "charging_station", "operator": "EV-Time", "name": "EV-Time", "_source": "worldwide"}}, {"type": "node", "id": 12543390092, "lat": 59.870348, "lon": 30.533444, "tags": {"amenity": "charging_station", "operator": "EV-Time", "name": "EV-Time", "_source": "worldwide"}}, {"type": "node", "id": 12644334888, "lat": 59.965665, "lon": 30.283968, "tags": {"amenity": "charging_station", "fee": "yes", "access": "customers", "network": "TOUCH", "operator": "Touch", "name": "Touch", "capacity": "2", "_source": "worldwide"}}, {"type": "node", "id": 12849271454, "lat": 59.915398, "lon": 30.344709, "tags": {"amenity": "charging_station", "fee": "yes", "access": "yes", "brand": "Punkt E", "name": "Punkt E", "_source": "worldwide"}}, {"type": "node", "id": 12953436441, "lat": 59.926439, "lon": 30.238717, "tags": {"amenity": "charging_station", "fee": "yes", "name": "Punkt E", "_source": "worldwide"}}, {"type": "node", "id": 13107853624, "lat": 59.853531, "lon": 30.21857, "tags": {"amenity": "charging_station", "access": "yes", "name": "EV Charging Station", "socket:chademo": "1", "capacity": "2", "_source": "worldwide"}}, {"type": "node", "id": 13208388808, "lat": 59.971505, "lon": 30.274335, "tags": {"amenity": "charging_station", "name": "EV Charging Station", "_source": "worldwide"}}, {"type": "node", "id": 13284214155, "lat": 59.988927, "lon": 30.254308, "tags": {"amenity": "charging_station", "fee": "yes", "name": "EV Charging Station", "_source": "worldwide"}}, {"type": "node", "id": 13284214156, "lat": 59.988928, "lon": 30.254242, "tags": {"amenity": "charging_station", "fee": "yes", "name": "EV Charging Station", "_source": "worldwide"}}, {"type": "node", "id": 13320029939, "lat": 59.98008, "lon": 30.333218, "tags": {"amenity": "charging_station", "brand": "Яндекс.Заправки", "name": "Яндекс.Заправки", "_source": "worldwide"}}, {"type": "node", "id": 13320465301, "lat": 59.837991, "lon": 30.204463, "tags": {"amenity": "charging_station", "opening_hours": "24/7", "operator": "Бери заряд", "name": "Бери заряд", "addr:street": "проспект Маршала Жукова", "addr:housenumber": "60 к1 литВ", "_source": "worldwide"}}, {"type": "node", "id": 13374240309, "lat": 59.909903, "lon": 30.446316, "tags": {"amenity": "charging_station", "fee": "yes", "access": "yes", "name": "EV Charging Station", "_source": "worldwide"}}, {"type": "node", "id": 13381230862, "lat": 59.959195, "lon": 30.40525, "tags": {"amenity": "charging_station", "fee": "yes", "brand": "Punkt E", "name": "Punkt E", "socket:chademo": "2", "capacity": "4", "_source": "worldwide"}}, {"type": "node", "id": 13434423280, "lat": 59.947637, "lon": 30.478684, "tags": {"amenity": "charging_station", "fee": "yes", "access": "yes", "opening_hours": "24/7", "name": "EV Charging Station", "socket:chademo": "1", "capacity": "3", "_source": "worldwide"}}, {"type": "node", "id": 13532367436, "lat": 59.908336, "lon": 30.5178, "tags": {"amenity": "charging_station", "name": "EV Charging Station", "_source": "worldwide"}}, {"type": "node", "id": 13532367452, "lat": 59.909872, "lon": 30.517067, "tags": {"amenity": "charging_station", "access": "private", "name": "EV Charging Station", "_source": "worldwide"}}, {"type": "node", "id": 13532367464, "lat": 59.908775, "lon": 30.516717, "tags": {"amenity": "charging_station", "name": "EV Charging Station", "_source": "worldwide"}}, {"type": "node", "id": 13608041879, "lat": 59.996563, "lon": 30.304686, "tags": {"amenity": "charging_station", "brand": "Яндекс.Заправки", "name": "Яндекс.Заправки", "_source": "worldwide"}}, {"type": "node", "id": 13644829946, "lat": 59.809522, "lon": 30.085604, "tags": {"amenity": "charging_station", "operator": "Ev-Time", "name": "Ev-Time", "_source": "worldwide"}}, {"type": "node", "id": 13709877501, "lat": 59.868177, "lon": 30.23962, "tags": {"amenity": "charging_station", "opening_hours": "24/7", "name": "Электрохаб Первомайский", "addr:street": "дорога на Турухтанные острова", "addr:housenumber": "14/2", "_source": "worldwide"}}]}