{"id": "29-117", "latMin": 29, "lonMin": 117, "latMax": 30, "lonMax": 118, "generated": "2026-04-16T18:39:07.266Z", "count": 10, "pois": [{"type": "node", "id": 11078261879, "lat": 29.318821, "lon": 117.895067, "tags": {"amenity": "charging_station", "brand": "国家电网", "operator": "国家电网有限公司", "name": "国家电网", "_source": "worldwide"}}, {"type": "node", "id": 11078261880, "lat": 29.316861, "lon": 117.89492, "tags": {"amenity": "charging_station", "brand": "国家电网", "operator": "国家电网有限公司", "name": "国家电网", "_source": "worldwide"}}, {"type": "node", "id": 11826477794, "lat": 29.262201, "lon": 117.061983, "tags": {"amenity": "charging_station", "brand": "国家电网", "operator": "国家电网有限公司", "name": "国家电网", "_source": "worldwide"}}, {"type": "node", "id": 11826477795, "lat": 29.266157, "lon": 117.063147, "tags": {"amenity": "charging_station", "brand": "国家电网", "operator": "国家电网有限公司", "name": "国家电网", "_source": "worldwide"}}, {"type": "node", "id": 11828485487, "lat": 29.96886, "lon": 117.02713, "tags": {"amenity": "charging_station", "brand": "国家电网", "operator": "国家电网有限公司", "name": "国家电网", "_source": "worldwide"}}, {"type": "node", "id": 11828485488, "lat": 29.972174, "lon": 117.025583, "tags": {"amenity": "charging_station", "brand": "国家电网", "operator": "国家电网有限公司", "name": "国家电网", "_source": "worldwide"}}, {"type": "node", "id": 12311784427, "lat": 29.309278, "lon": 117.351724, "tags": {"amenity": "charging_station", "brand": "国家电网", "operator": "国家电网有限公司", "name": "国家电网", "_source": "worldwide"}}, {"type": "node", "id": 12311784428, "lat": 29.309025, "lon": 117.349425, "tags": {"amenity": "charging_station", "brand": "国家电网", "operator": "国家电网有限公司", "name": "国家电网", "_source": "worldwide"}}, {"type": "node", "id": 12311793607, "lat": 29.245484, "lon": 117.723998, "tags": {"amenity": "charging_station", "brand": "国家电网", "operator": "国家电网有限公司", "name": "国家电网", "_source": "worldwide"}}, {"type": "node", "id": 12311793608, "lat": 29.241855, "lon": 117.725664, "tags": {"amenity": "charging_station", "brand": "国家电网", "operator": "国家电网有限公司", "name": "国家电网", "_source": "worldwide"}}]}