{"id": "41-25", "latMin": 41, "lonMin": 25, "latMax": 42, "lonMax": 26, "generated": "2026-04-16T18:39:07.846Z", "count": 46, "pois": [{"type": "node", "id": 10942366145, "lat": 41.919561, "lon": 25.55788, "tags": {"amenity": "charging_station", "fee": "yes", "operator": "GigaCharger", "name": "GigaCharger", "capacity": "1", "_source": "worldwide"}}, {"type": "node", "id": 12120250400, "lat": 41.931115, "lon": 25.603662, "tags": {"amenity": "charging_station", "fee": "yes", "access": "yes", "opening_hours": "24/7", "brand": "Fines Charging", "network": "FINES Charging", "operator": "Финес Енерджи ООД", "name": "FINES Техномаркет Хасково", "addr:street": "бул. Съединение", "addr:housenumber": "77", "addr:postcode": "6304", "addr:city": "Хасково", "addr:country": "BG", "socket:chademo": "1", "capacity": "4", "_source": "worldwide"}}, {"type": "node", "id": 12120304833, "lat": 41.940065, "lon": 25.557901, "tags": {"amenity": "charging_station", "fee": "yes", "access": "yes", "opening_hours": "24/7", "brand": "Fines Charging", "network": "FINES Charging", "operator": "Финес Енерджи ООД", "name": "FINES Хасково Бриколаж", "addr:street": "Дунав", "addr:housenumber": "51", "addr:postcode": "6303", "addr:city": "Хасково", "addr:country": "BG", "capacity": "2", "_source": "worldwide"}}, {"type": "node", "id": 12124254063, "lat": 41.339883, "lon": 25.358213, "tags": {"amenity": "charging_station", "fee": "yes", "access": "yes", "opening_hours": "24/7", "brand": "Fines Charging", "network": "Fines Charging", "operator": "Финес Енерджи ООД", "name": "Fines - Златоград", "capacity": "2", "_source": "worldwide"}}, {"type": "node", "id": 12141934996, "lat": 41.92544, "lon": 25.920916, "tags": {"amenity": "charging_station", "fee": "yes", "access": "yes", "opening_hours": "24/7", "brand": "Fines Charging", "network": "Fines Charging", "operator": "Финес Енерджи ООД", "name": "Fines - Harmanli", "addr:postcode": "6450", "addr:city": "Харманли", "addr:country": "BG", "capacity": "4", "_source": "worldwide"}}, {"type": "node", "id": 12146280201, "lat": 41.94095, "lon": 25.555183, "tags": {"amenity": "charging_station", "fee": "yes", "access": "yes", "opening_hours": "24/7", "brand": "Fines Charging", "network": "Fines Charging", "operator": "Финес Енерджи ООД", "name": "Fines - Retail Park Haskovo DC", "capacity": "2", "_source": "worldwide"}}, {"type": "node", "id": 12151195680, "lat": 41.606791, "lon": 25.375401, "tags": {"amenity": "charging_station", "fee": "yes", "access": "yes", "opening_hours": "24/7", "brand": "Fines Charging", "network": "Fines Charging", "operator": "Финес Енерджи ООД", "name": "Fines - IDA Kardzhali", "capacity": "4", "_source": "worldwide"}}, {"type": "node", "id": 12157597111, "lat": 41.379287, "lon": 25.101947, "tags": {"amenity": "charging_station", "fee": "yes", "access": "yes", "opening_hours": "24/7", "brand": "Fines Charging", "network": "Fines Charging", "operator": "Финес Енерджи ЕООД", "name": "Fines - Златоград", "capacity": "2", "_source": "worldwide"}}, {"type": "node", "id": 12506733657, "lat": 41.114352, "lon": 25.378445, "tags": {"amenity": "charging_station", "fee": "yes", "access": "yes", "opening_hours": "24/7", "brand": "nrg incharge", "operator": "Shell Coral gas", "name": "nrg - Shell Coral gas", "addr:postcode": "69100", "addr:city": "Κομοτηνή", "socket:chademo": "1", "capacity": "3", "_source": "worldwide"}}, {"type": "node", "id": 12521554312, "lat": 41.026117, "lon": 25.687804, "tags": {"amenity": "charging_station", "fee": "yes", "access": "yes", "opening_hours": "Mo-Fr 08:00-21:00; Sa 08:00-20:00", "brand": "DEI Blue", "operator": "ΑΒ Βασιλόπουλος", "name": "DEI blue - ΑΒ Βασιλόπουλος", "addr:postcode": "69300", "addr:city": "Σάπες", "capacity": "4", "_source": "worldwide"}}, {"type": "node", "id": 12524620883, "lat": 41.125158, "lon": 25.393846, "tags": {"amenity": "charging_station", "fee": "yes", "access": "yes", "opening_hours": "24/7", "brand": "nrg incharge", "operator": "Εμπορικό Κέντρο Kosmopolis", "name": "nrg - Kosmopolis", "addr:postcode": "69100", "addr:city": "Κομοτηνή", "capacity": "3", "_source": "worldwide"}}, {"type": "node", "id": 12524620884, "lat": 41.125851, "lon": 25.392685, "tags": {"amenity": "charging_station", "fee": "yes", "access": "yes", "opening_hours": "24/7", "brand": "DEI Blue", "operator": "Σκλαβενίτης", "name": "DΕΙ blue - Σκλαβενίτης", "addr:postcode": "69100", "addr:city": "Κομοτηνή", "capacity": "6", "_source": "worldwide"}}, {"type": "node", "id": 12524620885, "lat": 41.126811, "lon": 25.391217, "tags": {"amenity": "charging_station", "fee": "yes", "access": "yes", "opening_hours": "24/7", "brand": "DEI Blue", "operator": "ΑΒ Βασιλόπουλος", "name": "DEI blue - ΑΒ Βασιλόπουλος", "addr:postcode": "69100", "addr:city": "Κομοτηνή", "capacity": "8", "_source": "worldwide"}}, {"type": "node", "id": 12524623386, "lat": 41.121029, "lon": 25.637369, "tags": {"amenity": "charging_station", "fee": "yes", "access": "yes", "opening_hours": "24/7", "brand": "nrg incharge", "operator": "AVIN", "name": "nrg - AVIN Φίλλυρα", "addr:postcode": "69500", "addr:city": "Φίλλυρα", "capacity": "1", "_source": "worldwide"}}, {"type": "node", "id": 12524632122, "lat": 41.099034, "lon": 25.442716, "tags": {"amenity": "charging_station", "fee": "yes", "access": "yes", "opening_hours": "24/7", "brand": "DEI Blue", "operator": "ELIN ΤΑΠΑΤΖΑ", "name": "DΕΙ blue - ELIN Ταπατζά", "addr:postcode": "69100", "addr:city": "Κομοτηνή", "socket:chademo": "1", "capacity": "3", "_source": "worldwide"}}, {"type": "node", "id": 12524632123, "lat": 41.099029, "lon": 25.440173, "tags": {"amenity": "charging_station", "fee": "yes", "access": "yes", "opening_hours": "24/7", "brand": "nrg incharge", "operator": "Avin", "name": "nrg - AVIN", "addr:postcode": "69100", "addr:city": "Κομοτηνή", "socket:chademo": "1", "capacity": "3", "_source": "worldwide"}}, {"type": "node", "id": 12524745706, "lat": 41.10874, "lon": 25.353866, "tags": {"amenity": "charging_station", "fee": "yes", "access": "yes", "opening_hours": "24/7", "brand": "nrg incharge", "operator": "AVIN", "name": "nrg - AVIN Κομοτηνή", "addr:street": "Ξάνθης - Κομοτηνής", "addr:postcode": "69100", "addr:city": "Κομοτηνή", "capacity": "2", "_source": "worldwide"}}, {"type": "node", "id": 12525023087, "lat": 41.006245, "lon": 25.119614, "tags": {"amenity": "charging_station", "fee": "yes", "access": "yes", "opening_hours": "24/7", "brand": "Joltie", "operator": "Λιμενικό Ταμείο Πόρτο Λάγος", "name": "Joltie - Πόρτο Λάγος", "addr:postcode": "67063", "capacity": "2", "_source": "worldwide"}}, {"type": "node", "id": 12525038196, "lat": 41.108134, "lon": 25.416293, "tags": {"amenity": "charging_station", "fee": "yes", "access": "yes", "opening_hours": "Mo-Su 06:00-22:00", "brand": "nrg incharge", "operator": "Shell 144", "name": "nrg - Shell 144", "addr:postcode": "69100", "addr:city": "Κομοτηνή", "capacity": "3", "_source": "worldwide"}}, {"type": "node", "id": 12525038197, "lat": 41.109114, "lon": 25.414156, "tags": {"amenity": "charging_station", "fee": "yes", "access": "yes", "opening_hours": "24/7", "brand": "EKO Charge&Go", "operator": "BP ΤΖΑΜΠΑΖΛΗΣ", "name": "EKO Charge&Go - BP Κομοτηνή", "addr:postcode": "69100", "addr:city": "Κομοτηνή", "capacity": "2", "_source": "worldwide"}}, {"type": "node", "id": 12525038198, "lat": 41.110668, "lon": 25.413315, "tags": {"amenity": "charging_station", "fee": "yes", "access": "yes", "opening_hours": "Mo-Fr 09:00-17:00; Sa 09:00-13:00", "brand": "Chargespot", "operator": "Autopark Melkonian", "name": "Chargespot - Autopark Melkonian", "addr:street": "Κωνσταντίνου Σισμάνογλου", "addr:housenumber": "51", "addr:postcode": "69100", "addr:city": "Κομοτηνή", "capacity": "2", "_source": "worldwide"}}, {"type": "node", "id": 12525038199, "lat": 41.119453, "lon": 25.409021, "tags": {"amenity": "charging_station", "fee": "yes", "access": "yes", "opening_hours": "24/7", "brand": "Joltie", "operator": "Parking Κομοτηνής", "name": "Joltie - Parking Κομοτηνής", "addr:street": "Δημοκρατίας", "addr:postcode": "69099", "addr:city": "Κομοτηνή", "capacity": "1", "_source": "worldwide"}}, {"type": "node", "id": 12525038200, "lat": 41.119316, "lon": 25.410781, "tags": {"amenity": "charging_station", "fee": "yes", "access": "yes", "opening_hours": "24/7", "brand": "nrg incharge", "operator": "Μασούτης", "name": "nrg - Μασούτης Κομοτηνή Δημοκρατίας", "addr:street": "Δημοκρατίας", "addr:housenumber": "40", "addr:postcode": "69133", "addr:city": "Κομοτηνή", "capacity": "2", "_source": "worldwide"}}, {"type": "node", "id": 12525050501, "lat": 41.113656, "lon": 25.402707, "tags": {"amenity": "charging_station", "fee": "yes", "access": "yes", "opening_hours": "24/7", "brand": "nrg incharge", "operator": "Μασούτης", "name": "nrg - Μασούτης Grand", "addr:street": "Σταματίου Κουμπάρη", "addr:housenumber": "12", "addr:postcode": "69133", "addr:city": "Κομοτηνή", "capacity": "2", "_source": "worldwide"}}, {"type": "node", "id": 12525050502, "lat": 41.112724, "lon": 25.400954, "tags": {"amenity": "charging_station", "fee": "yes", "access": "yes", "opening_hours": "24/7", "brand": "DEI Blue", "operator": "Σκλαβενίτης", "name": "DΕΙ blue - Σκλαβενίτης", "addr:street": "Κοσμίου", "addr:housenumber": "5", "addr:postcode": "69100", "addr:city": "Κομοτηνή", "capacity": "8", "_source": "worldwide"}}, {"type": "node", "id": 12525050503, "lat": 41.118078, "lon": 25.391386, "tags": {"amenity": "charging_station", "fee": "yes", "access": "yes", "opening_hours": "24/7", "brand": "DEI Blue", "operator": "Σκλαβενίτης", "name": "DΕΙ blue - Σκλαβενίτης", "addr:street": "Νικολάου Πλαστήρα", "addr:housenumber": "8", "addr:postcode": "69100", "addr:city": "Κομοτηνή", "capacity": "2", "_source": "worldwide"}}, {"type": "node", "id": 12923671100, "lat": 41.127595, "lon": 25.390469, "tags": {"amenity": "charging_station", "fee": "yes", "access": "yes", "opening_hours": "24/7", "brand": "Electrip", "operator": "Super Store", "name": "Electrip - Super Store", "addr:postcode": "69100", "addr:city": "Κομοτηνή", "capacity": "4", "_source": "worldwide"}}, {"type": "node", "id": 13152368795, "lat": 41.109752, "lon": 25.364696, "tags": {"amenity": "charging_station", "fee": "yes", "access": "yes", "opening_hours": "24/7", "brand": "ChargePlus", "network": "eVplus", "operator": "METRO C&C Κομοτηνή", "name": "ChargePlus - METRO C&C", "addr:postcode": "69100", "addr:city": "Κομοτηνή", "capacity": "2", "_source": "worldwide"}}, {"type": "node", "id": 13161427453, "lat": 41.114544, "lon": 25.382919, "tags": {"amenity": "charging_station", "fee": "yes", "access": "yes", "opening_hours": "24/7", "brand": "Chargespot", "operator": "VW Μαυρίδης", "name": "Chargespot - VW Μαυρίδης", "addr:street": "Εθνάρχου Μακαρίου", "addr:postcode": "69132", "addr:city": "Κομοτηνή", "capacity": "2", "_source": "worldwide"}}, {"type": "node", "id": 13264944649, "lat": 41.023494, "lon": 25.692487, "tags": {"amenity": "charging_station", "fee": "yes", "access": "yes", "opening_hours": "24/7", "brand": "EV Loader", "network": "EV Loader", "operator": "Street 1 Cafe", "name": "EV Loader - Street 1 Cafe", "addr:street": "Αντωνίου Παπαδήμα", "addr:housenumber": "1", "addr:postcode": "69300", "addr:city": "Σάπες", "capacity": "1", "_source": "worldwide"}}, {"type": "node", "id": 13375622064, "lat": 41.332079, "lon": 25.364513, "tags": {"amenity": "charging_station", "fee": "yes", "access": "yes", "opening_hours": "24/7", "brand": "Fines Charging", "network": "Fines Charging", "name": "Fines - NRJSoft Hotel Kirkovo", "capacity": "3", "_source": "worldwide"}}, {"type": "node", "id": 13381422324, "lat": 41.927207, "lon": 25.907567, "tags": {"amenity": "charging_station", "fee": "yes", "access": "yes", "opening_hours": "24/7", "brand": "Fines Charging", "network": "Fines Charging", "name": "Fines - Harmanli SIMS - 2011", "addr:street": "Бенковска", "addr:housenumber": "31", "addr:postcode": "6450", "addr:city": "Харманли", "capacity": "1", "_source": "worldwide"}}, {"type": "node", "id": 13382586338, "lat": 41.929781, "lon": 25.569796, "tags": {"amenity": "charging_station", "fee": "yes", "access": "yes", "opening_hours": "24/7", "brand": "Fines Charging", "network": "Fines Charging", "name": "Fines - Hotel Vigor Haskovo", "capacity": "4", "_source": "worldwide"}}, {"type": "node", "id": 13382586339, "lat": 41.948811, "lon": 25.557584, "tags": {"amenity": "charging_station", "fee": "yes", "access": "yes", "opening_hours": "24/7", "brand": "Fines Charging", "network": "Fines Charging", "name": "Fines - NRJSoft Contrast Haskovo", "capacity": "1", "_source": "worldwide"}}, {"type": "node", "id": 13387329367, "lat": 41.112315, "lon": 25.373915, "tags": {"amenity": "charging_station", "fee": "yes", "access": "yes", "opening_hours": "24/7", "brand": "DEI Blue", "operator": "Ζαχαροπλαστείο Νεντίμ", "name": "DEI blue - Ζαχαροπλαστείο Νεντίμ", "addr:postcode": "69100", "addr:city": "Κομοτηνή", "capacity": "2", "_source": "worldwide"}}, {"type": "node", "id": 13391295296, "lat": 41.613877, "lon": 25.374926, "tags": {"amenity": "charging_station", "fee": "yes", "access": "yes", "opening_hours": "24/7", "brand": "Eldrive", "name": "Eldrive - Orpheus Kardzhali", "capacity": "4", "_source": "worldwide"}}, {"type": "node", "id": 13391295297, "lat": 41.630292, "lon": 25.37757, "tags": {"amenity": "charging_station", "fee": "yes", "access": "yes", "opening_hours": "24/7", "brand": "Eldrive", "name": "Eldrive - Technopolis Kardzhali", "capacity": "2", "_source": "worldwide"}}, {"type": "node", "id": 13394459150, "lat": 41.756285, "lon": 25.353489, "tags": {"amenity": "charging_station", "fee": "yes", "access": "yes", "opening_hours": "24/7", "brand": "Eldrive", "name": "Eldrive - Technostroy Engineering", "capacity": "1", "_source": "worldwide"}}, {"type": "node", "id": 13394459680, "lat": 41.931662, "lon": 25.605409, "tags": {"amenity": "charging_station", "fee": "yes", "access": "yes", "opening_hours": "Mo-Fr 10:00-20:00; Sa-Su 10:00-19:00", "brand": "Eldrive", "name": "Eldrive - Technopolis Haskovo", "capacity": "2", "_source": "worldwide"}}, {"type": "node", "id": 13394462962, "lat": 41.969879, "lon": 25.560476, "tags": {"amenity": "charging_station", "fee": "yes", "access": "yes", "opening_hours": "Mo-Su 08:00-20:00", "brand": "Eldrive", "name": "Eldrive - Holiday Park Haskovo", "capacity": "4", "_source": "worldwide"}}, {"type": "node", "id": 13394462963, "lat": 41.956658, "lon": 25.512032, "tags": {"amenity": "charging_station", "fee": "yes", "access": "yes", "opening_hours": "24/7", "brand": "Eldrive", "name": "Eldrive - Hotel Druzhba Haskovo", "socket:chademo": "1", "capacity": "2", "_source": "worldwide"}}, {"type": "node", "id": 13479015558, "lat": 41.109351, "lon": 25.348541, "tags": {"amenity": "charging_station", "fee": "yes", "access": "yes", "opening_hours": "24/7", "brand": "Electrip", "operator": "Zen Outlet & More", "name": "Electrip - Zen Outlet Κομοτηνή", "addr:postcode": "69100", "addr:city": "Κομοτηνή", "capacity": "2", "_source": "worldwide"}}, {"type": "node", "id": 13677013039, "lat": 41.94398, "lon": 25.543068, "tags": {"amenity": "charging_station", "fee": "yes", "access": "yes", "opening_hours": "24/7", "brand": "Electrip", "network": "Electrip", "name": "Electrip - Hotel Fantasia", "addr:city": "Хасково", "capacity": "2", "_source": "worldwide"}}, {"type": "node", "id": 13718399301, "lat": 41.106571, "lon": 25.363813, "tags": {"amenity": "charging_station", "fee": "yes", "access": "yes", "opening_hours": "24/7", "brand": "Chargespot", "operator": "Alesco", "name": "Chargespot - Alesco ΕΚΟ Κομοτηνή DC", "addr:postcode": "69100", "addr:city": "Κομοτηνή", "capacity": "2", "_source": "worldwide"}}, {"type": "node", "id": 13722518964, "lat": 41.10717, "lon": 25.419615, "tags": {"amenity": "charging_station", "fee": "no", "access": "customers", "opening_hours": "Mo-Sa 07:45-21:00; Su 11:00-18:00; PH off", "brand": "Lidl", "operator": "Lidl", "name": "Lidl Κομοτηνή", "addr:street": "Κομοτηνής - Αλεξανδρούπολης", "addr:postcode": "69100", "addr:city": "Κομοτηνή", "capacity": "2", "_source": "worldwide"}}, {"type": "node", "id": 13723507420, "lat": 41.09841, "lon": 25.443971, "tags": {"amenity": "charging_station", "fee": "yes", "access": "yes", "opening_hours": "24/7", "brand": "nrg incharge", "operator": "Αρχοντικό Χρήστου & Εύης", "name": "nrg - Αρχοντικό Χρήστου & Εύης", "addr:postcode": "69100", "addr:city": "Κομοτηνή", "capacity": "2", "_source": "worldwide"}}]}