{"id": "46--120", "latMin": 46, "lonMin": -120, "latMax": 47, "lonMax": -119, "generated": "2026-04-16T18:39:08.114Z", "count": 30, "pois": [{"type": "node", "id": 6296949377, "lat": 46.250643, "lon": -119.115027, "tags": {"amenity": "charging_station", "access": "customers", "brand": "Tesla, Inc.", "operator": "Tesla, Inc.", "name": "Tesla Destination Charger", "_source": "worldwide"}}, {"type": "node", "id": 7004870978, "lat": 46.242199, "lon": -119.124278, "tags": {"amenity": "charging_station", "fee": "yes", "opening_hours": "24/7", "network": "Greenlots", "name": "EV Charging Station", "socket:chademo": "1", "socket:type1_combo": "1", "capacity": "2", "_source": "worldwide"}}, {"type": "node", "id": 7004870979, "lat": 46.2422, "lon": -119.124224, "tags": {"amenity": "charging_station", "fee": "yes", "opening_hours": "24/7", "network": "Greenlots", "name": "EV Charging Station", "socket:type1": "1", "capacity": "1", "_source": "worldwide"}}, {"type": "node", "id": 10297504953, "lat": 46.228924, "lon": -119.106771, "tags": {"amenity": "charging_station", "access": "yes", "brand": "Blink", "operator": "Blink", "name": "Blink", "_source": "worldwide"}}, {"type": "node", "id": 10711529414, "lat": 46.18, "lon": -119.188267, "tags": {"amenity": "charging_station", "access": "yes", "brand": "greenlots", "operator": "Shell Recharge Solutions", "name": "greenlots", "socket:chademo": "1", "socket:type1_combo": "1", "capacity": "2", "_source": "worldwide"}}, {"type": "node", "id": 10767377993, "lat": 46.256717, "lon": -119.118376, "tags": {"amenity": "charging_station", "access": "customers", "name": "EV Charging Station", "_source": "worldwide"}}, {"type": "node", "id": 10813182256, "lat": 46.348445, "lon": -119.269651, "tags": {"amenity": "charging_station", "access": "private", "operator": "Port of Benton", "name": "Port of Benton", "_source": "worldwide"}}, {"type": "node", "id": 10817187598, "lat": 46.238403, "lon": -119.236553, "tags": {"amenity": "charging_station", "access": "private", "brand": "enel x", "name": "enel x", "_source": "worldwide"}}, {"type": "node", "id": 10847489168, "lat": 46.225965, "lon": -119.120215, "tags": {"amenity": "charging_station", "access": "private", "name": "EV Charging Station", "_source": "worldwide"}}, {"type": "node", "id": 10861337204, "lat": 46.179978, "lon": -119.188249, "tags": {"amenity": "charging_station", "access": "yes", "brand": "FLO", "operator": "FLO", "name": "FLO", "socket:type1": "1", "capacity": "1", "_source": "worldwide"}}, {"type": "node", "id": 10866017926, "lat": 46.2926, "lon": -119.274736, "tags": {"amenity": "charging_station", "access": "customers", "name": "EV Charging Station", "_source": "worldwide"}}, {"type": "node", "id": 10900974619, "lat": 46.281011, "lon": -119.273077, "tags": {"amenity": "charging_station", "access": "customers", "name": "EV Charging Station", "socket:type1": "2", "capacity": "4", "_source": "worldwide"}}, {"type": "node", "id": 10927684044, "lat": 46.195201, "lon": -119.266053, "tags": {"amenity": "charging_station", "brand": "Shell Recharge", "operator": "Shell Recharge Solutions", "name": "Shell Recharge", "_source": "worldwide"}}, {"type": "node", "id": 11023078143, "lat": 46.213029, "lon": -119.16227, "tags": {"amenity": "charging_station", "name": "EV Charging Station", "_source": "worldwide"}}, {"type": "node", "id": 11133038861, "lat": 46.241917, "lon": -119.121665, "tags": {"amenity": "charging_station", "name": "EV Charging Station", "_source": "worldwide"}}, {"type": "node", "id": 11172727848, "lat": 46.212837, "lon": -119.160847, "tags": {"amenity": "charging_station", "name": "EV Charging Station", "_source": "worldwide"}}, {"type": "node", "id": 11179487439, "lat": 46.217356, "lon": -119.131857, "tags": {"amenity": "charging_station", "access": "unknown", "name": "EV Charging Station", "_source": "worldwide"}}, {"type": "node", "id": 11179487493, "lat": 46.217234, "lon": -119.132684, "tags": {"amenity": "charging_station", "access": "unknown", "name": "EV Charging Station", "_source": "worldwide"}}, {"type": "node", "id": 11225066882, "lat": 46.233828, "lon": -119.219858, "tags": {"amenity": "charging_station", "access": "unknown", "name": "EV Charging Station", "_source": "worldwide"}}, {"type": "node", "id": 11733108311, "lat": 46.261913, "lon": -119.22181, "tags": {"amenity": "charging_station", "operator": "SemaConnect", "name": "SemaConnect", "_source": "worldwide"}}, {"type": "node", "id": 12145120298, "lat": 46.215954, "lon": -119.21854, "tags": {"amenity": "charging_station", "access": "customers", "name": "EV Charging Station", "_source": "worldwide"}}, {"type": "node", "id": 12167321648, "lat": 46.219455, "lon": -119.789815, "tags": {"amenity": "charging_station", "name": "EV Charging Station", "_source": "worldwide"}}, {"type": "node", "id": 12173975251, "lat": 46.241194, "lon": -119.116958, "tags": {"amenity": "charging_station", "access": "customers", "operator": "Bruchi's", "name": "Bruchi's", "_source": "worldwide"}}, {"type": "node", "id": 12292719548, "lat": 46.280002, "lon": -119.276047, "tags": {"amenity": "charging_station", "name": "EV Charging Station", "_source": "worldwide"}}, {"type": "node", "id": 12475045583, "lat": 46.256348, "lon": -119.178956, "tags": {"amenity": "charging_station", "access": "private", "name": "EV Charging Station", "_source": "worldwide"}}, {"type": "node", "id": 13021867239, "lat": 46.197927, "lon": -119.162967, "tags": {"amenity": "charging_station", "brand": "Electrify America", "operator": "Electrify America", "name": "Electrify America", "_source": "worldwide"}}, {"type": "node", "id": 13043532395, "lat": 46.260017, "lon": -119.319138, "tags": {"amenity": "charging_station", "name": "EV Charging Station", "_source": "worldwide"}}, {"type": "node", "id": 13049032429, "lat": 46.211055, "lon": -119.167588, "tags": {"amenity": "charging_station", "fee": "no", "brand": "ChargePoint", "operator": "ChargePoint", "name": "ChargePoint", "_source": "worldwide"}}, {"type": "node", "id": 13240030109, "lat": 46.176874, "lon": -119.185245, "tags": {"amenity": "charging_station", "brand": "ChargePoint", "operator": "ChargePoint", "name": "ChargePoint", "_source": "worldwide"}}, {"type": "node", "id": 13480424543, "lat": 46.333859, "lon": -119.273266, "tags": {"amenity": "charging_station", "name": "EV Charging Station", "_source": "worldwide"}}]}