{"id": "61-28", "latMin": 61, "lonMin": 28, "latMax": 62, "lonMax": 29, "generated": "2026-04-16T18:39:08.797Z", "count": 15, "pois": [{"type": "node", "id": 5583138494, "lat": 61.866098, "lon": 28.887063, "tags": {"amenity": "charging_station", "fee": "no", "operator": "Lumme energia", "name": "Lumme energia", "capacity": "2", "_source": "worldwide"}}, {"type": "node", "id": 5583138495, "lat": 61.868561, "lon": 28.886135, "tags": {"amenity": "charging_station", "fee": "no", "brand": "Recharge", "operator": "Recharge", "name": "Recharge", "capacity": "2", "_source": "worldwide"}}, {"type": "node", "id": 5583138496, "lat": 61.868863, "lon": 28.882414, "tags": {"amenity": "charging_station", "fee": "no", "brand": "Recharge", "operator": "Recharge", "name": "Recharge", "capacity": "2", "_source": "worldwide"}}, {"type": "node", "id": 5583138497, "lat": 61.870361, "lon": 28.880122, "tags": {"amenity": "charging_station", "fee": "yes", "brand": "Recharge", "operator": "Recharge", "name": "Recharge", "capacity": "2", "_source": "worldwide"}}, {"type": "node", "id": 7064893277, "lat": 61.044832, "lon": 28.20213, "tags": {"amenity": "charging_station", "fee": "yes", "operator": "K-Lataus", "name": "K-Lataus (K-Citymarket Lappeenranta)", "_source": "worldwide"}}, {"type": "node", "id": 7064894134, "lat": 61.044405, "lon": 28.179993, "tags": {"amenity": "charging_station", "fee": "yes", "operator": "K-Lataus", "name": "K-Lataus (Neste K Lappeenranta)", "_source": "worldwide"}}, {"type": "node", "id": 7064907673, "lat": 61.186643, "lon": 28.743932, "tags": {"amenity": "charging_station", "fee": "yes", "name": "K-Lataus (Neste K Imatra)", "_source": "worldwide"}}, {"type": "node", "id": 7064915234, "lat": 61.057162, "lon": 28.18454, "tags": {"amenity": "charging_station", "fee": "yes", "operator": "K-Lataus", "name": "K-Lataus (K-Supermarket Rakuuna)", "_source": "worldwide"}}, {"type": "node", "id": 9355659367, "lat": 61.052676, "lon": 28.261149, "tags": {"amenity": "charging_station", "fee": "yes", "access": "yes", "opening_hours": "24/7", "brand": "Tesla Supercharger", "operator": "Tesla", "name": "Lappeenranta Supercharger", "addr:street": "Hirsimäenkatu", "addr:housenumber": "1", "addr:postcode": "53500", "addr:city": "Lappeenranta", "addr:country": "FI", "capacity": "8", "_source": "worldwide"}}, {"type": "node", "id": 9846711772, "lat": 61.575036, "lon": 28.147545, "tags": {"amenity": "charging_station", "name": "EV Charging Station", "_source": "worldwide"}}, {"type": "node", "id": 11384369758, "lat": 61.877405, "lon": 28.828282, "tags": {"amenity": "charging_station", "brand": "ABC-lataus", "name": "ABC-lataus", "_source": "worldwide"}}, {"type": "node", "id": 11384369759, "lat": 61.879035, "lon": 28.814099, "tags": {"amenity": "charging_station", "brand": "K-lataus", "operator": "K-Lataus", "name": "K-lataus", "_source": "worldwide"}}, {"type": "node", "id": 11384369760, "lat": 61.864771, "lon": 28.940346, "tags": {"amenity": "charging_station", "brand": "K-lataus", "name": "K-lataus", "_source": "worldwide"}}, {"type": "node", "id": 12025404626, "lat": 61.059093, "lon": 28.184279, "tags": {"amenity": "charging_station", "brand": "VIRTA", "operator": "VIRTA", "name": "VIRTA", "_source": "worldwide"}}, {"type": "node", "id": 12037933651, "lat": 61.044284, "lon": 28.215434, "tags": {"amenity": "charging_station", "fee": "yes", "name": "EV Charging Station", "_source": "worldwide"}}]}